Workbook

Sheet 1. Balance General
A1: ISAGEN S.A. E.S.P.
A2: ESTADO DE SITUACIÓN FINANCIERA
A3: Valores en millones de pesos colombianos (COP)
A5: CONCEPTO | B5: 2020 | C5: 2021 | D5: 2022 | E5: 2023 | F5: 2024 | G5: 2025 (Sep)
A6: ACTIVOS NO CORRIENTES
A7: Propiedades, planta y equipo, neto | B7: 15179609 | C7: 17230679 | D7: 17365315 | E7: 17742271 | F7: 17522981 | G7: 17319341
A8: Activos intangibles, neto | B8: 2774772 | C8: 2783815 | D8: 2755491 | E8: 2760600 | F8: 2769524 | G8: 2783735
A9: Cuentas por cobrar, neto | B9: 26655 | C9: 24142 | D9: 2024312 | E9: 1910168 | F9: 32960 | G9: 60923
A10: Instrumentos financieros | B10: 84 | C10: 84 | D10: 84 | E10: 84 | F10: 2493808 | G10: 544561
A11: Operaciones con derivados | B11: - | C11: 85660 | D11: 228189 | E11: 31816 | F11: 90034 | G11: 1202870
A12: Efectivo restringido | B12: 2127 | C12: 2185 | D12: 2159 | E12: 2541 | F12: 2928 | G12: 27114
A13: Otros activos | B13: 950 | C13: 950 | D13: 950 | G13: 3230
A14: Total Activos No Corrientes | B14: 17984197 | C14: 20127515 | D14: 22376500 | E14: 22447480 | F14: 22912235 | G14: 21941774
A16: ACTIVOS CORRIENTES
A17: Inventarios | B17: 34138 | C17: 35705 | D17: 27889 | E17: 29526 | F17: 33172 | G17: 41304
A18: Cuentas por cobrar, neto | B18: 514164 | C18: 663842 | D18: 883971 | E18: 934414 | F18: 815437 | G18: 735617
A19: Instrumentos financieros | B19: 84 | C19: 84 | D19: 84 | E19: 84 | F19: 2493808 | G19: 2716711
A20: Activos por impuestos | B20: 434 | C20: 52077 | D20: 1919 | E20: 7372 | F20: 21940 | G20: 70638
A21: Otros activos | B21: 11708 | C21: 28345 | D21: 57682 | E21: 26385 | F21: 38012 | G21: 143617
A22: Operaciones con derivados | B22: - | C22: 24079 | D22: 150851 | E22: 61809 | F22: 25205 | G22: 48341
A23: Efectivo restringido | B23: 261 | C23: 16901 | D23: 50 | E23: 50 | F23: 50 | G23: 8297
A24: Efectivo y equivalentes de efectivo | B24: 83749 | C24: 172827 | D24: 309200 | E24: 220352 | F24: 447198 | G24: 229542
A25: Total Activos Corrientes | B25: 644454 | C25: 993776 | D25: 1431562 | E25: 1279908 | F25: 1381014 | G25: 3923479
A26: nan
A27: TOTAL ACTIVOS | B27: 18628651 | C27: 21121291 | D27: 23808062 | E27: 23727388 | F27: 24293249 | G27: 25865253
A28: nan
A29: PATRIMONIO
A30: Capital | B30: 141552 | C30: 141552 | D30: 141552 | E30: 141552 | F30: 141552 | G30: 141552
A31: Reservas | B31: 2006640 | C31: 1580616 | D31: 660660 | E31: 863781 | F31: 1140297 | G31: 1550093
A32: Superávit de capital | B32: 2074259 | C32: 2074259 | D32: 2074259 | E32: 2074259 | F32: 2074259 | G32: 2074259
A33: Ganancias retenidas | B33: 1268261 | C33: 1268261 | D33: 1268261 | E33: 1268261 | F33: 1268350 | G33: 1268350
A34: Otro resultado integral | B34: -28353 | C34: 91255 | D34: 185776 | E34: 46069 | F34: 32508 | G34: 47436
A35: Resultado integral total periodo (Utilidad Neta) | B35: 496129 | C35: 523127 | D35: 1233838 | E35: 1035242 | F35: 904616 | G35: 606104
A36: Total Patrimonio de los Accionistas | B36: 5958488 | C36: 5679070 | D36: 5564346 | E36: 5429164 | F36: 5561582 | G36: 5687794
A37: nan
A38: PASIVOS NO CORRIENTES
A39: Operaciones de financiamiento | B39: 5834931 | C39: 7132894 | D39: 9781531 | E39: 9814359 | F39: 10148678 | G39: 10985428
A40: Obligaciones con vinculados | B40: 2767416 | C40: 3434629 | D40: 2540445 | E40: 2541954 | F40: 2542108 | G40: 2538988
A41: Operaciones con derivados | B41: 13150 | C41: - | D41: 18602 | E41: 3781 | F41: 11065 | G41: -
A42: Impuestos, contribuciones y tasas | B42: 3458998 | C42: 4208665 | D42: 4423094 | E42: 4506519 | F42: 4654129 | G42: 4753643
A43: Beneficios a empleados | B43: 135963 | C43: 125550 | D43: 99556 | E43: 150693 | F43: 130726 | G43: 126769
A44: Provisiones | B44: 26673 | C44: 22005 | D44: 45138 | E44: 62904 | F44: 35280 | G44: 37130
A45: Cuentas por pagar | B45: 1902 | C45: 1956 | D45: 2159 | E45: 2541 | F45: 2928 | G45: 3230
A46: Total Pasivos No Corrientes | B46: 12239033 | C46: 14925699 | D46: 16910525 | E46: 17082751 | F46: 17524914 | G46: 18515826
A47: nan
A48: PASIVOS CORRIENTES
A49: Operaciones de financiamiento | B49: 184414 | C49: 232182 | D49: 736514 | E49: 747995 | F49: 749154 | G49: 864080
A50: Cuentas por pagar | B50: 129972 | C50: 169907 | D50: 233323 | E50: 250856 | F50: 270730 | G50: 494062
A51: Obligaciones con vinculados | B51: 1459 | C51: 1908 | D51: 6335 | E51: 9321 | F51: 3107 | G51: 1554
A52: Operaciones con derivados | B52: 43188 | C52: 2968 | D52: 35914 | E52: 38965 | F52: 22239 | G52: 91772
A53: Impuestos, contribuciones y tasas | B53: 24130 | C53: 64123 | D53: 267227 | E53: 118520 | F53: 20614 | G53: 37454
A54: Beneficios a empleados | B54: 27561 | C54: 29362 | D54: 26419 | E54: 33037 | F54: 33518 | G54: 44126
A55: Provisiones | B55: 2274 | C55: 1887 | D55: 1757 | E55: 5226 | F55: 19199 | G55: 11161
A56: Otros pasivos | B56: 18132 | C56: 14185 | D56: 25702 | E56: 11553 | F56: 88192 | G56: 117424
A57: Total Pasivos Corrientes | B57: 431130 | C57: 516522 | D57: 1333191 | E57: 1215473 | F57: 1206753 | G57: 1661633
A58: nan
A59: TOTAL PASIVOS | B59: 12670163 | C59: 15442221 | D59: 18243716 | E59: 18298224 | F59: 18731667 | G59: 20177459
A60: TOTAL PATRIMONIO Y PASIVOS | B60: 18628651 | C60: 21121291 | D60: 23808062 | E60: 23727388 | F60: 24293249 | G60: 25865253

Sheet 2. Estado de Resultados
A1: ISAGEN S.A. E.S.P.
A2: ESTADO DE RESULTADOS INTEGRAL
A3: Valores en millones de pesos colombianos (COP)
A5: CONCEPTO | B5: 2020 | C5: 2021 | D5: 2022 | E5: 2023 | F5: 2024 | G5: 2025 (9m)
A6: Ingresos de contratos con clientes | B6: 3211250 | C6: 3481508 | D6: 4816990 | E6: 5523362 | F6: 6095701 | G6: 3847514
A7: Costo de ventas | B7: -1531443 | C7: -1345155 | D7: -1601980 | E7: -2427742 | F7: -3156150 | G7: -1505886
A8: Utilidad Bruta | B8: =SUM(B6:B7) | C8: =SUM(C6:C7) | D8: =SUM(D6:D7) | E8: =SUM(E6:E7) | F8: =SUM(F6:F7) | G8: =SUM(G6:G7)
A9: Otros ingresos | B9: 36002 | C9: 5951 | D9: 5082 | E9: 9704 | F9: 37485 | G9: 6665
A10: Gastos de administración | B10: -132538 | C10: -124062 | D10: -155931 | E10: -161731 | F10: -184607 | G10: -130464
A11: Otros gastos | B11: -13003 | C11: -8191 | D11: -94550 | E11: -37608 | F11: -53946 | G11: -38386
A12: Ingresos financieros | B12: 22992 | C12: 8278 | D12: 198968 | E12: 414971 | F12: 416117 | G12: 226003
A13: Gastos financieros | B13: -821768 | C13: -731988 | D13: -1317580 | E13: -1821155 | F13: -1870991 | G13: -1360062
A14: Diferencia en cambio, neta | B14: -34923 | C14: 7 | D14: -27239 | E14: 61822 | F14: -19632 | G14: -250894
A15: Utilidad Antes de Impuestos | B15: 736569 | C15: 1286348 | D15: 1823760 | E15: 1561623 | F15: 1263977 | G15: 794490
A16: EBIT | B16: =B15-B13-B12 | C16: =C15-C13-C12 | D16: =D15-D13-D12 | E16: =E15-E13-E12 | F16: =F15-F13-F12 | G16: =G15-G13-G12
A17: Depreciación | B17: 229772 | C17: 233257 | D17: 259748 | E17: 279121 | F17: 304317 | G17: 235541
A18: Amortización | B18: 1864 | C18: 3444 | D18: 2712 | E18: 2728 | F18: 5711 | G18: 3472
A19: EBITDA | B19: =B16+B17+B18 | C19: =C16+C17+C18 | D19: =D16+D17+D18 | E19: =E16+E17+E18 | F19: =F16+F17+F18 | G19: =G16+G17+G18
A20: Impuesto de renta - Corriente | B20: -165680 | C20: -70862 | D20: -467248 | E20: -326019 | F20: -234854 | G20: -91087
A21: Impuesto de renta - Diferido | B21: -74760 | C21: -692359 | D21: -167874 | E21: -151518 | F21: -154288 | G21: -92160
A22: Utilidad Neta del Periodo | B22: 496129 | C22: 523127 | D22: 1233838 | E22: 1035242 | F22: 904616 | G22: 606104
A25: OTRO RESULTADO INTEGRAL (ORI)
A26: Ganancias actuariales (Beneficios definidos) | B26: 1015 | C26: 10906 | D26: 17374 | E26: -27643 | F26: 10416
A27: Coberturas flujo de efectivo | B27: -29050 | C27: 108702 | D27: 73128 | E27: -112064 | F27: -23977
A28: Total Otro Resultado Integral, neto | B28: -28035 | C28: 119608 | D28: 94521 | E28: -139707 | F28: -13561 | G28: 14928
A29: RESULTADO INTEGRAL TOTAL | B29: 468094 | C29: 642735 | D29: 1328359 | E29: 895535 | F29: 891055 | G29: 621032
A30: nan
A31: Utilidad básica y diluida por acción ($) | B31: 405 | C31: 427 | D31: 1008 | E31: 846 | F31: 739 | G31: 495

Sheet 3. Análisis Vertical BSC
A1: ISAGEN S.A. E.S.P.
A2: ANÁLISIS VERTICAL - BALANCE GENERAL
A3: Composición porcentual respecto al Total de Activos (%)
A5: CONCEPTO | B5: 2020 | C5: 2021 | D5: 2022 | E5: 2023 | F5: 2024 | G5: 2025 (Sep)
A6: ACTIVOS NO CORRIENTES | B6: =('1. Balance General'!B6/'1. Balance General'!B27)*100 | C6: =('1. Balance General'!C6/'1. Balance General'!C27)*100 | D6: =('1. Balance General'!D6/'1. Balance General'!D27)*100 | E6: =('1. Balance General'!E6/'1. Balance General'!E27)*100 | F6: =('1. Balance General'!F6/'1. Balance General'!F27)*100 | G6: =('1. Balance General'!G6/'1. Balance General'!G27)*100
A7: Propiedades, planta y equipo, neto | B7: =('1. Balance General'!B7/'1. Balance General'!B27)*100 | C7: =('1. Balance General'!C7/'1. Balance General'!C27)*100 | D7: =('1. Balance General'!D7/'1. Balance General'!D27)*100 | E7: =('1. Balance General'!E7/'1. Balance General'!E27)*100 | F7: =('1. Balance General'!F7/'1. Balance General'!F27)*100 | G7: =('1. Balance General'!G7/'1. Balance General'!G27)*100
A8: Activos intangibles, neto | B8: =('1. Balance General'!B8/'1. Balance General'!B27)*100 | C8: =('1. Balance General'!C8/'1. Balance General'!C27)*100 | D8: =('1. Balance General'!D8/'1. Balance General'!D27)*100 | E8: =('1. Balance General'!E8/'1. Balance General'!E27)*100 | F8: =('1. Balance General'!F8/'1. Balance General'!F27)*100 | G8: =('1. Balance General'!G8/'1. Balance General'!G27)*100
A9: Cuentas por cobrar, neto | B9: =('1. Balance General'!B9/'1. Balance General'!B27)*100 | C9: =('1. Balance General'!C9/'1. Balance General'!C27)*100 | D9: =('1. Balance General'!D9/'1. Balance General'!D27)*100 | E9: =('1. Balance General'!E9/'1. Balance General'!E27)*100 | F9: =('1. Balance General'!F9/'1. Balance General'!F27)*100 | G9: =('1. Balance General'!G9/'1. Balance General'!G27)*100
A10: Instrumentos financieros | B10: =('1. Balance General'!B10/'1. Balance General'!B27)*100 | C10: =('1. Balance General'!C10/'1. Balance General'!C27)*100 | D10: =('1. Balance General'!D10/'1. Balance General'!D27)*100 | E10: =('1. Balance General'!E10/'1. Balance General'!E27)*100 | F10: =('1. Balance General'!F10/'1. Balance General'!F27)*100 | G10: =('1. Balance General'!G10/'1. Balance General'!G27)*100
A11: Operaciones con derivados | B11: =('1. Balance General'!B11/'1. Balance General'!B27)*100 | C11: =('1. Balance General'!C11/'1. Balance General'!C27)*100 | D11: =('1. Balance General'!D11/'1. Balance General'!D27)*100 | E11: =('1. Balance General'!E11/'1. Balance General'!E27)*100 | F11: =('1. Balance General'!F11/'1. Balance General'!F27)*100 | G11: =('1. Balance General'!G11/'1. Balance General'!G27)*100
A12: Efectivo restringido | B12: =('1. Balance General'!B12/'1. Balance General'!B27)*100 | C12: =('1. Balance General'!C12/'1. Balance General'!C27)*100 | D12: =('1. Balance General'!D12/'1. Balance General'!D27)*100 | E12: =('1. Balance General'!E12/'1. Balance General'!E27)*100 | F12: =('1. Balance General'!F12/'1. Balance General'!F27)*100 | G12: =('1. Balance General'!G12/'1. Balance General'!G27)*100
A13: Otros activos | B13: =('1. Balance General'!B13/'1. Balance General'!B27)*100 | C13: =('1. Balance General'!C13/'1. Balance General'!C27)*100 | D13: =('1. Balance General'!D13/'1. Balance General'!D27)*100 | E13: =('1. Balance General'!E13/'1. Balance General'!E27)*100 | F13: =('1. Balance General'!F13/'1. Balance General'!F27)*100 | G13: =('1. Balance General'!G13/'1. Balance General'!G27)*100
A14: Total Activos No Corrientes | B14: =('1. Balance General'!B14/'1. Balance General'!B27)*100 | C14: =('1. Balance General'!C14/'1. Balance General'!C27)*100 | D14: =('1. Balance General'!D14/'1. Balance General'!D27)*100 | E14: =('1. Balance General'!E14/'1. Balance General'!E27)*100 | F14: =('1. Balance General'!F14/'1. Balance General'!F27)*100 | G14: =('1. Balance General'!G14/'1. Balance General'!G27)*100
A16: ACTIVOS CORRIENTES | B16: =('1. Balance General'!B16/'1. Balance General'!B27)*100 | C16: =('1. Balance General'!C16/'1. Balance General'!C27)*100 | D16: =('1. Balance General'!D16/'1. Balance General'!D27)*100 | E16: =('1. Balance General'!E16/'1. Balance General'!E27)*100 | F16: =('1. Balance General'!F16/'1. Balance General'!F27)*100 | G16: =('1. Balance General'!G16/'1. Balance General'!G27)*100
A17: Inventarios | B17: =('1. Balance General'!B17/'1. Balance General'!B27)*100 | C17: =('1. Balance General'!C17/'1. Balance General'!C27)*100 | D17: =('1. Balance General'!D17/'1. Balance General'!D27)*100 | E17: =('1. Balance General'!E17/'1. Balance General'!E27)*100 | F17: =('1. Balance General'!F17/'1. Balance General'!F27)*100 | G17: =('1. Balance General'!G17/'1. Balance General'!G27)*100
A18: Cuentas por cobrar, neto | B18: =('1. Balance General'!B18/'1. Balance General'!B27)*100 | C18: =('1. Balance General'!C18/'1. Balance General'!C27)*100 | D18: =('1. Balance General'!D18/'1. Balance General'!D27)*100 | E18: =('1. Balance General'!E18/'1. Balance General'!E27)*100 | F18: =('1. Balance General'!F18/'1. Balance General'!F27)*100 | G18: =('1. Balance General'!G18/'1. Balance General'!G27)*100
A19: Instrumentos financieros | B19: =('1. Balance General'!B19/'1. Balance General'!B27)*100 | C19: =('1. Balance General'!C19/'1. Balance General'!C27)*100 | D19: =('1. Balance General'!D19/'1. Balance General'!D27)*100 | E19: =('1. Balance General'!E19/'1. Balance General'!E27)*100 | F19: =('1. Balance General'!F19/'1. Balance General'!F27)*100 | G19: =('1. Balance General'!G19/'1. Balance General'!G27)*100
A20: Activos por impuestos | B20: =('1. Balance General'!B20/'1. Balance General'!B27)*100 | C20: =('1. Balance General'!C20/'1. Balance General'!C27)*100 | D20: =('1. Balance General'!D20/'1. Balance General'!D27)*100 | E20: =('1. Balance General'!E20/'1. Balance General'!E27)*100 | F20: =('1. Balance General'!F20/'1. Balance General'!F27)*100 | G20: =('1. Balance General'!G20/'1. Balance General'!G27)*100
A21: Otros activos | B21: =('1. Balance General'!B21/'1. Balance General'!B27)*100 | C21: =('1. Balance General'!C21/'1. Balance General'!C27)*100 | D21: =('1. Balance General'!D21/'1. Balance General'!D27)*100 | E21: =('1. Balance General'!E21/'1. Balance General'!E27)*100 | F21: =('1. Balance General'!F21/'1. Balance General'!F27)*100 | G21: =('1. Balance General'!G21/'1. Balance General'!G27)*100
A22: Operaciones con derivados | B22: =('1. Balance General'!B22/'1. Balance General'!B27)*100 | C22: =('1. Balance General'!C22/'1. Balance General'!C27)*100 | D22: =('1. Balance General'!D22/'1. Balance General'!D27)*100 | E22: =('1. Balance General'!E22/'1. Balance General'!E27)*100 | F22: =('1. Balance General'!F22/'1. Balance General'!F27)*100 | G22: =('1. Balance General'!G22/'1. Balance General'!G27)*100
A23: Efectivo restringido | B23: =('1. Balance General'!B23/'1. Balance General'!B27)*100 | C23: =('1. Balance General'!C23/'1. Balance General'!C27)*100 | D23: =('1. Balance General'!D23/'1. Balance General'!D27)*100 | E23: =('1. Balance General'!E23/'1. Balance General'!E27)*100 | F23: =('1. Balance General'!F23/'1. Balance General'!F27)*100 | G23: =('1. Balance General'!G23/'1. Balance General'!G27)*100
A24: Efectivo y equivalentes de efectivo | B24: =('1. Balance General'!B24/'1. Balance General'!B27)*100 | C24: =('1. Balance General'!C24/'1. Balance General'!C27)*100 | D24: =('1. Balance General'!D24/'1. Balance General'!D27)*100 | E24: =('1. Balance General'!E24/'1. Balance General'!E27)*100 | F24: =('1. Balance General'!F24/'1. Balance General'!F27)*100 | G24: =('1. Balance General'!G24/'1. Balance General'!G27)*100
A25: Total Activos Corrientes | B25: =('1. Balance General'!B25/'1. Balance General'!B27)*100 | C25: =('1. Balance General'!C25/'1. Balance General'!C27)*100 | D25: =('1. Balance General'!D25/'1. Balance General'!D27)*100 | E25: =('1. Balance General'!E25/'1. Balance General'!E27)*100 | F25: =('1. Balance General'!F25/'1. Balance General'!F27)*100 | G25: =('1. Balance General'!G25/'1. Balance General'!G27)*100
A27: TOTAL ACTIVOS | B27: =('1. Balance General'!B27/'1. Balance General'!B27)*100 | C27: =('1. Balance General'!C27/'1. Balance General'!C27)*100 | D27: =('1. Balance General'!D27/'1. Balance General'!D27)*100 | E27: =('1. Balance General'!E27/'1. Balance General'!E27)*100 | F27: =('1. Balance General'!F27/'1. Balance General'!F27)*100 | G27: =('1. Balance General'!G27/'1. Balance General'!G27)*100
A29: PATRIMONIO | B29: =('1. Balance General'!B29/'1. Balance General'!B27)*100 | C29: =('1. Balance General'!C29/'1. Balance General'!C27)*100 | D29: =('1. Balance General'!D29/'1. Balance General'!D27)*100 | E29: =('1. Balance General'!E29/'1. Balance General'!E27)*100 | F29: =('1. Balance General'!F29/'1. Balance General'!F27)*100 | G29: =('1. Balance General'!G29/'1. Balance General'!G27)*100
A30: Capital | B30: =('1. Balance General'!B30/'1. Balance General'!B27)*100 | C30: =('1. Balance General'!C30/'1. Balance General'!C27)*100 | D30: =('1. Balance General'!D30/'1. Balance General'!D27)*100 | E30: =('1. Balance General'!E30/'1. Balance General'!E27)*100 | F30: =('1. Balance General'!F30/'1. Balance General'!F27)*100 | G30: =('1. Balance General'!G30/'1. Balance General'!G27)*100
A31: Reservas | B31: =('1. Balance General'!B31/'1. Balance General'!B27)*100 | C31: =('1. Balance General'!C31/'1. Balance General'!C27)*100 | D31: =('1. Balance General'!D31/'1. Balance General'!D27)*100 | E31: =('1. Balance General'!E31/'1. Balance General'!E27)*100 | F31: =('1. Balance General'!F31/'1. Balance General'!F27)*100 | G31: =('1. Balance General'!G31/'1. Balance General'!G27)*100
A32: Superávit de capital | B32: =('1. Balance General'!B32/'1. Balance General'!B27)*100 | C32: =('1. Balance General'!C32/'1. Balance General'!C27)*100 | D32: =('1. Balance General'!D32/'1. Balance General'!D27)*100 | E32: =('1. Balance General'!E32/'1. Balance General'!E27)*100 | F32: =('1. Balance General'!F32/'1. Balance General'!F27)*100 | G32: =('1. Balance General'!G32/'1. Balance General'!G27)*100
A33: Ganancias retenidas | B33: =('1. Balance General'!B33/'1. Balance General'!B27)*100 | C33: =('1. Balance General'!C33/'1. Balance General'!C27)*100 | D33: =('1. Balance General'!D33/'1. Balance General'!D27)*100 | E33: =('1. Balance General'!E33/'1. Balance General'!E27)*100 | F33: =('1. Balance General'!F33/'1. Balance General'!F27)*100 | G33: =('1. Balance General'!G33/'1. Balance General'!G27)*100
A34: Otro resultado integral | B34: =('1. Balance General'!B34/'1. Balance General'!B27)*100 | C34: =('1. Balance General'!C34/'1. Balance General'!C27)*100 | D34: =('1. Balance General'!D34/'1. Balance General'!D27)*100 | E34: =('1. Balance General'!E34/'1. Balance General'!E27)*100 | F34: =('1. Balance General'!F34/'1. Balance General'!F27)*100 | G34: =('1. Balance General'!G34/'1. Balance General'!G27)*100
A35: Resultado integral total periodo (Utilidad Neta) | B35: =('1. Balance General'!B35/'1. Balance General'!B27)*100 | C35: =('1. Balance General'!C35/'1. Balance General'!C27)*100 | D35: =('1. Balance General'!D35/'1. Balance General'!D27)*100 | E35: =('1. Balance General'!E35/'1. Balance General'!E27)*100 | F35: =('1. Balance General'!F35/'1. Balance General'!F27)*100 | G35: =('1. Balance General'!G35/'1. Balance General'!G27)*100
A36: Total Patrimonio de los Accionistas | B36: =('1. Balance General'!B36/'1. Balance General'!B27)*100 | C36: =('1. Balance General'!C36/'1. Balance General'!C27)*100 | D36: =('1. Balance General'!D36/'1. Balance General'!D27)*100 | E36: =('1. Balance General'!E36/'1. Balance General'!E27)*100 | F36: =('1. Balance General'!F36/'1. Balance General'!F27)*100 | G36: =('1. Balance General'!G36/'1. Balance General'!G27)*100
A38: PASIVOS NO CORRIENTES | B38: =('1. Balance General'!B38/'1. Balance General'!B27)*100 | C38: =('1. Balance General'!C38/'1. Balance General'!C27)*100 | D38: =('1. Balance General'!D38/'1. Balance General'!D27)*100 | E38: =('1. Balance General'!E38/'1. Balance General'!E27)*100 | F38: =('1. Balance General'!F38/'1. Balance General'!F27)*100 | G38: =('1. Balance General'!G38/'1. Balance General'!G27)*100
A39: Operaciones de financiamiento | B39: =('1. Balance General'!B39/'1. Balance General'!B27)*100 | C39: =('1. Balance General'!C39/'1. Balance General'!C27)*100 | D39: =('1. Balance General'!D39/'1. Balance General'!D27)*100 | E39: =('1. Balance General'!E39/'1. Balance General'!E27)*100 | F39: =('1. Balance General'!F39/'1. Balance General'!F27)*100 | G39: =('1. Balance General'!G39/'1. Balance General'!G27)*100
A40: Obligaciones con vinculados | B40: =('1. Balance General'!B40/'1. Balance General'!B27)*100 | C40: =('1. Balance General'!C40/'1. Balance General'!C27)*100 | D40: =('1. Balance General'!D40/'1. Balance General'!D27)*100 | E40: =('1. Balance General'!E40/'1. Balance General'!E27)*100 | F40: =('1. Balance General'!F40/'1. Balance General'!F27)*100 | G40: =('1. Balance General'!G40/'1. Balance General'!G27)*100
A41: Operaciones con derivados | B41: =('1. Balance General'!B41/'1. Balance General'!B27)*100 | C41: =('1. Balance General'!C41/'1. Balance General'!C27)*100 | D41: =('1. Balance General'!D41/'1. Balance General'!D27)*100 | E41: =('1. Balance General'!E41/'1. Balance General'!E27)*100 | F41: =('1. Balance General'!F41/'1. Balance General'!F27)*100 | G41: =('1. Balance General'!G41/'1. Balance General'!G27)*100
A42: Impuestos, contribuciones y tasas | B42: =('1. Balance General'!B42/'1. Balance General'!B27)*100 | C42: =('1. Balance General'!C42/'1. Balance General'!C27)*100 | D42: =('1. Balance General'!D42/'1. Balance General'!D27)*100 | E42: =('1. Balance General'!E42/'1. Balance General'!E27)*100 | F42: =('1. Balance General'!F42/'1. Balance General'!F27)*100 | G42: =('1. Balance General'!G42/'1. Balance General'!G27)*100
A43: Beneficios a empleados | B43: =('1. Balance General'!B43/'1. Balance General'!B27)*100 | C43: =('1. Balance General'!C43/'1. Balance General'!C27)*100 | D43: =('1. Balance General'!D43/'1. Balance General'!D27)*100 | E43: =('1. Balance General'!E43/'1. Balance General'!E27)*100 | F43: =('1. Balance General'!F43/'1. Balance General'!F27)*100 | G43: =('1. Balance General'!G43/'1. Balance General'!G27)*100
A44: Provisiones | B44: =('1. Balance General'!B44/'1. Balance General'!B27)*100 | C44: =('1. Balance General'!C44/'1. Balance General'!C27)*100 | D44: =('1. Balance General'!D44/'1. Balance General'!D27)*100 | E44: =('1. Balance General'!E44/'1. Balance General'!E27)*100 | F44: =('1. Balance General'!F44/'1. Balance General'!F27)*100 | G44: =('1. Balance General'!G44/'1. Balance General'!G27)*100
A45: Cuentas por pagar | B45: =('1. Balance General'!B45/'1. Balance General'!B27)*100 | C45: =('1. Balance General'!C45/'1. Balance General'!C27)*100 | D45: =('1. Balance General'!D45/'1. Balance General'!D27)*100 | E45: =('1. Balance General'!E45/'1. Balance General'!E27)*100 | F45: =('1. Balance General'!F45/'1. Balance General'!F27)*100 | G45: =('1. Balance General'!G45/'1. Balance General'!G27)*100
A46: Total Pasivos No Corrientes | B46: =('1. Balance General'!B46/'1. Balance General'!B27)*100 | C46: =('1. Balance General'!C46/'1. Balance General'!C27)*100 | D46: =('1. Balance General'!D46/'1. Balance General'!D27)*100 | E46: =('1. Balance General'!E46/'1. Balance General'!E27)*100 | F46: =('1. Balance General'!F46/'1. Balance General'!F27)*100 | G46: =('1. Balance General'!G46/'1. Balance General'!G27)*100
A48: PASIVOS CORRIENTES | B48: =('1. Balance General'!B48/'1. Balance General'!B27)*100 | C48: =('1. Balance General'!C48/'1. Balance General'!C27)*100 | D48: =('1. Balance General'!D48/'1. Balance General'!D27)*100 | E48: =('1. Balance General'!E48/'1. Balance General'!E27)*100 | F48: =('1. Balance General'!F48/'1. Balance General'!F27)*100 | G48: =('1. Balance General'!G48/'1. Balance General'!G27)*100
A49: Operaciones de financiamiento | B49: =('1. Balance General'!B49/'1. Balance General'!B27)*100 | C49: =('1. Balance General'!C49/'1. Balance General'!C27)*100 | D49: =('1. Balance General'!D49/'1. Balance General'!D27)*100 | E49: =('1. Balance General'!E49/'1. Balance General'!E27)*100 | F49: =('1. Balance General'!F49/'1. Balance General'!F27)*100 | G49: =('1. Balance General'!G49/'1. Balance General'!G27)*100
A50: Cuentas por pagar | B50: =('1. Balance General'!B50/'1. Balance General'!B27)*100 | C50: =('1. Balance General'!C50/'1. Balance General'!C27)*100 | D50: =('1. Balance General'!D50/'1. Balance General'!D27)*100 | E50: =('1. Balance General'!E50/'1. Balance General'!E27)*100 | F50: =('1. Balance General'!F50/'1. Balance General'!F27)*100 | G50: =('1. Balance General'!G50/'1. Balance General'!G27)*100
A51: Obligaciones con vinculados | B51: =('1. Balance General'!B51/'1. Balance General'!B27)*100 | C51: =('1. Balance General'!C51/'1. Balance General'!C27)*100 | D51: =('1. Balance General'!D51/'1. Balance General'!D27)*100 | E51: =('1. Balance General'!E51/'1. Balance General'!E27)*100 | F51: =('1. Balance General'!F51/'1. Balance General'!F27)*100 | G51: =('1. Balance General'!G51/'1. Balance General'!G27)*100
A52: Operaciones con derivados | B52: =('1. Balance General'!B52/'1. Balance General'!B27)*100 | C52: =('1. Balance General'!C52/'1. Balance General'!C27)*100 | D52: =('1. Balance General'!D52/'1. Balance General'!D27)*100 | E52: =('1. Balance General'!E52/'1. Balance General'!E27)*100 | F52: =('1. Balance General'!F52/'1. Balance General'!F27)*100 | G52: =('1. Balance General'!G52/'1. Balance General'!G27)*100
A53: Impuestos, contribuciones y tasas | B53: =('1. Balance General'!B53/'1. Balance General'!B27)*100 | C53: =('1. Balance General'!C53/'1. Balance General'!C27)*100 | D53: =('1. Balance General'!D53/'1. Balance General'!D27)*100 | E53: =('1. Balance General'!E53/'1. Balance General'!E27)*100 | F53: =('1. Balance General'!F53/'1. Balance General'!F27)*100 | G53: =('1. Balance General'!G53/'1. Balance General'!G27)*100
A54: Beneficios a empleados | B54: =('1. Balance General'!B54/'1. Balance General'!B27)*100 | C54: =('1. Balance General'!C54/'1. Balance General'!C27)*100 | D54: =('1. Balance General'!D54/'1. Balance General'!D27)*100 | E54: =('1. Balance General'!E54/'1. Balance General'!E27)*100 | F54: =('1. Balance General'!F54/'1. Balance General'!F27)*100 | G54: =('1. Balance General'!G54/'1. Balance General'!G27)*100
A55: Provisiones | B55: =('1. Balance General'!B55/'1. Balance General'!B27)*100 | C55: =('1. Balance General'!C55/'1. Balance General'!C27)*100 | D55: =('1. Balance General'!D55/'1. Balance General'!D27)*100 | E55: =('1. Balance General'!E55/'1. Balance General'!E27)*100 | F55: =('1. Balance General'!F55/'1. Balance General'!F27)*100 | G55: =('1. Balance General'!G55/'1. Balance General'!G27)*100
A56: Otros pasivos | B56: =('1. Balance General'!B56/'1. Balance General'!B27)*100 | C56: =('1. Balance General'!C56/'1. Balance General'!C27)*100 | D56: =('1. Balance General'!D56/'1. Balance General'!D27)*100 | E56: =('1. Balance General'!E56/'1. Balance General'!E27)*100 | F56: =('1. Balance General'!F56/'1. Balance General'!F27)*100 | G56: =('1. Balance General'!G56/'1. Balance General'!G27)*100

Sheet 4. Análisis Horizontal BSC
A1: ISAGEN S.A. E.S.P.
A2: ANÁLISIS HORIZONTAL - BALANCE GENERAL
A3: Variación porcentual interanual (%)
A5: CONCEPTO | B5: 2020-2021 | C5: 2021-2022 | D5: 2022-2023 | E5: 2023-2024 | F5: 2024-2025
A6: ACTIVOS NO CORRIENTES
A7: Propiedades, planta y equipo, neto | B7: =(('1. Balance General'!C7-'1. Balance General'!B7)/'1. Balance General'!B7)*100 | C7: =(('1. Balance General'!D7-'1. Balance General'!C7)/'1. Balance General'!C7)*100 | D7: =(('1. Balance General'!E7-'1. Balance General'!D7)/'1. Balance General'!D7)*100 | E7: =(('1. Balance General'!F7-'1. Balance General'!E7)/'1. Balance General'!E7)*100 | F7: =(('1. Balance General'!G7-'1. Balance General'!F7)/'1. Balance General'!F7)*100
A8: Activos intangibles, neto | B8: =(('1. Balance General'!C8-'1. Balance General'!B8)/'1. Balance General'!B8)*100 | C8: =(('1. Balance General'!D8-'1. Balance General'!C8)/'1. Balance General'!C8)*100 | D8: =(('1. Balance General'!E8-'1. Balance General'!D8)/'1. Balance General'!D8)*100 | E8: =(('1. Balance General'!F8-'1. Balance General'!E8)/'1. Balance General'!E8)*100 | F8: =(('1. Balance General'!G8-'1. Balance General'!F8)/'1. Balance General'!F8)*100
A9: Cuentas por cobrar, neto | B9: =(('1. Balance General'!C9-'1. Balance General'!B9)/'1. Balance General'!B9)*100 | C9: =(('1. Balance General'!D9-'1. Balance General'!C9)/'1. Balance General'!C9)*100 | D9: =(('1. Balance General'!E9-'1. Balance General'!D9)/'1. Balance General'!D9)*100 | E9: =(('1. Balance General'!F9-'1. Balance General'!E9)/'1. Balance General'!E9)*100 | F9: =(('1. Balance General'!G9-'1. Balance General'!F9)/'1. Balance General'!F9)*100
A10: Instrumentos financieros | B10: =(('1. Balance General'!C10-'1. Balance General'!B10)/'1. Balance General'!B10)*100 | C10: =(('1. Balance General'!D10-'1. Balance General'!C10)/'1. Balance General'!C10)*100 | D10: =(('1. Balance General'!E10-'1. Balance General'!D10)/'1. Balance General'!D10)*100 | E10: =(('1. Balance General'!F10-'1. Balance General'!E10)/'1. Balance General'!E10)*100 | F10: =(('1. Balance General'!G10-'1. Balance General'!F10)/'1. Balance General'!F10)*100
A11: Operaciones con derivados | B11: =(('1. Balance General'!C11-'1. Balance General'!B11)/'1. Balance General'!B11)*100 | C11: =(('1. Balance General'!D11-'1. Balance General'!C11)/'1. Balance General'!C11)*100 | D11: =(('1. Balance General'!E11-'1. Balance General'!D11)/'1. Balance General'!D11)*100 | E11: =(('1. Balance General'!F11-'1. Balance General'!E11)/'1. Balance General'!E11)*100 | F11: =(('1. Balance General'!G11-'1. Balance General'!F11)/'1. Balance General'!F11)*100
A12: Efectivo restringido | B12: =(('1. Balance General'!C12-'1. Balance General'!B12)/'1. Balance General'!B12)*100 | C12: =(('1. Balance General'!D12-'1. Balance General'!C12)/'1. Balance General'!C12)*100 | D12: =(('1. Balance General'!E12-'1. Balance General'!D12)/'1. Balance General'!D12)*100 | E12: =(('1. Balance General'!F12-'1. Balance General'!E12)/'1. Balance General'!E12)*100 | F12: =(('1. Balance General'!G12-'1. Balance General'!F12)/'1. Balance General'!F12)*100
A13: Otros activos | B13: =(('1. Balance General'!C13-'1. Balance General'!B13)/'1. Balance General'!B13)*100 | C13: =(('1. Balance General'!D13-'1. Balance General'!C13)/'1. Balance General'!C13)*100 | D13: =(('1. Balance General'!E13-'1. Balance General'!D13)/'1. Balance General'!D13)*100 | E13: =(('1. Balance General'!F13-'1. Balance General'!E13)/'1. Balance General'!E13)*100 | F13: =(('1. Balance General'!G13-'1. Balance General'!F13)/'1. Balance General'!F13)*100
A14: Total Activos No Corrientes | B14: =(('1. Balance General'!C14-'1. Balance General'!B14)/'1. Balance General'!B14)*100 | C14: =(('1. Balance General'!D14-'1. Balance General'!C14)/'1. Balance General'!C14)*100 | D14: =(('1. Balance General'!E14-'1. Balance General'!D14)/'1. Balance General'!D14)*100 | E14: =(('1. Balance General'!F14-'1. Balance General'!E14)/'1. Balance General'!E14)*100 | F14: =(('1. Balance General'!G14-'1. Balance General'!F14)/'1. Balance General'!F14)*100
A16: ACTIVOS CORRIENTES
A17: Inventarios | B17: =(('1. Balance General'!C17-'1. Balance General'!B17)/'1. Balance General'!B17)*100 | C17: =(('1. Balance General'!D17-'1. Balance General'!C17)/'1. Balance General'!C17)*100 | D17: =(('1. Balance General'!E17-'1. Balance General'!D17)/'1. Balance General'!D17)*100 | E17: =(('1. Balance General'!F17-'1. Balance General'!E17)/'1. Balance General'!E17)*100 | F17: =(('1. Balance General'!G17-'1. Balance General'!F17)/'1. Balance General'!F17)*100
A18: Cuentas por cobrar, neto | B18: =(('1. Balance General'!C18-'1. Balance General'!B18)/'1. Balance General'!B18)*100 | C18: =(('1. Balance General'!D18-'1. Balance General'!C18)/'1. Balance General'!C18)*100 | D18: =(('1. Balance General'!E18-'1. Balance General'!D18)/'1. Balance General'!D18)*100 | E18: =(('1. Balance General'!F18-'1. Balance General'!E18)/'1. Balance General'!E18)*100 | F18: =(('1. Balance General'!G18-'1. Balance General'!F18)/'1. Balance General'!F18)*100
A19: Instrumentos financieros | B19: =(('1. Balance General'!C19-'1. Balance General'!B19)/'1. Balance General'!B19)*100 | C19: =(('1. Balance General'!D19-'1. Balance General'!C19)/'1. Balance General'!C19)*100 | D19: =(('1. Balance General'!E19-'1. Balance General'!D19)/'1. Balance General'!D19)*100 | E19: =(('1. Balance General'!F19-'1. Balance General'!E19)/'1. Balance General'!E19)*100 | F19: =(('1. Balance General'!G19-'1. Balance General'!F19)/'1. Balance General'!F19)*100
A20: Activos por impuestos | B20: =(('1. Balance General'!C20-'1. Balance General'!B20)/'1. Balance General'!B20)*100 | C20: =(('1. Balance General'!D20-'1. Balance General'!C20)/'1. Balance General'!C20)*100 | D20: =(('1. Balance General'!E20-'1. Balance General'!D20)/'1. Balance General'!D20)*100 | E20: =(('1. Balance General'!F20-'1. Balance General'!E20)/'1. Balance General'!E20)*100 | F20: =(('1. Balance General'!G20-'1. Balance General'!F20)/'1. Balance General'!F20)*100
A21: Otros activos | B21: =(('1. Balance General'!C21-'1. Balance General'!B21)/'1. Balance General'!B21)*100 | C21: =(('1. Balance General'!D21-'1. Balance General'!C21)/'1. Balance General'!C21)*100 | D21: =(('1. Balance General'!E21-'1. Balance General'!D21)/'1. Balance General'!D21)*100 | E21: =(('1. Balance General'!F21-'1. Balance General'!E21)/'1. Balance General'!E21)*100 | F21: =(('1. Balance General'!G21-'1. Balance General'!F21)/'1. Balance General'!F21)*100
A22: Operaciones con derivados | B22: =(('1. Balance General'!C22-'1. Balance General'!B22)/'1. Balance General'!B22)*100 | C22: =(('1. Balance General'!D22-'1. Balance General'!C22)/'1. Balance General'!C22)*100 | D22: =(('1. Balance General'!E22-'1. Balance General'!D22)/'1. Balance General'!D22)*100 | E22: =(('1. Balance General'!F22-'1. Balance General'!E22)/'1. Balance General'!E22)*100 | F22: =(('1. Balance General'!G22-'1. Balance General'!F22)/'1. Balance General'!F22)*100
A23: Efectivo restringido | B23: =(('1. Balance General'!C23-'1. Balance General'!B23)/'1. Balance General'!B23)*100 | C23: =(('1. Balance General'!D23-'1. Balance General'!C23)/'1. Balance General'!C23)*100 | D23: =(('1. Balance General'!E23-'1. Balance General'!D23)/'1. Balance General'!D23)*100 | E23: =(('1. Balance General'!F23-'1. Balance General'!E23)/'1. Balance General'!E23)*100 | F23: =(('1. Balance General'!G23-'1. Balance General'!F23)/'1. Balance General'!F23)*100
A24: Efectivo y equivalentes de efectivo | B24: =(('1. Balance General'!C24-'1. Balance General'!B24)/'1. Balance General'!B24)*100 | C24: =(('1. Balance General'!D24-'1. Balance General'!C24)/'1. Balance General'!C24)*100 | D24: =(('1. Balance General'!E24-'1. Balance General'!D24)/'1. Balance General'!D24)*100 | E24: =(('1. Balance General'!F24-'1. Balance General'!E24)/'1. Balance General'!E24)*100 | F24: =(('1. Balance General'!G24-'1. Balance General'!F24)/'1. Balance General'!F24)*100
A25: Total Activos Corrientes | B25: =(('1. Balance General'!C25-'1. Balance General'!B25)/'1. Balance General'!B25)*100 | C25: =(('1. Balance General'!D25-'1. Balance General'!C25)/'1. Balance General'!C25)*100 | D25: =(('1. Balance General'!E25-'1. Balance General'!D25)/'1. Balance General'!D25)*100 | E25: =(('1. Balance General'!F25-'1. Balance General'!E25)/'1. Balance General'!E25)*100 | F25: =(('1. Balance General'!G25-'1. Balance General'!F25)/'1. Balance General'!F25)*100
A27: TOTAL ACTIVOS | B27: =(('1. Balance General'!C27-'1. Balance General'!B27)/'1. Balance General'!B27)*100 | C27: =(('1. Balance General'!D27-'1. Balance General'!C27)/'1. Balance General'!C27)*100 | D27: =(('1. Balance General'!E27-'1. Balance General'!D27)/'1. Balance General'!D27)*100 | E27: =(('1. Balance General'!F27-'1. Balance General'!E27)/'1. Balance General'!E27)*100 | F27: =(('1. Balance General'!G27-'1. Balance General'!F27)/'1. Balance General'!F27)*100
A29: PATRIMONIO
A30: Capital | B30: =(('1. Balance General'!C30-'1. Balance General'!B30)/'1. Balance General'!B30)*100 | C30: =(('1. Balance General'!D30-'1. Balance General'!C30)/'1. Balance General'!C30)*100 | D30: =(('1. Balance General'!E30-'1. Balance General'!D30)/'1. Balance General'!D30)*100 | E30: =(('1. Balance General'!F30-'1. Balance General'!E30)/'1. Balance General'!E30)*100 | F30: =(('1. Balance General'!G30-'1. Balance General'!F30)/'1. Balance General'!F30)*100
A31: Reservas | B31: =(('1. Balance General'!C31-'1. Balance General'!B31)/'1. Balance General'!B31)*100 | C31: =(('1. Balance General'!D31-'1. Balance General'!C31)/'1. Balance General'!C31)*100 | D31: =(('1. Balance General'!E31-'1. Balance General'!D31)/'1. Balance General'!D31)*100 | E31: =(('1. Balance General'!F31-'1. Balance General'!E31)/'1. Balance General'!E31)*100 | F31: =(('1. Balance General'!G31-'1. Balance General'!F31)/'1. Balance General'!F31)*100
A32: Superávit de capital | B32: =(('1. Balance General'!C32-'1. Balance General'!B32)/'1. Balance General'!B32)*100 | C32: =(('1. Balance General'!D32-'1. Balance General'!C32)/'1. Balance General'!C32)*100 | D32: =(('1. Balance General'!E32-'1. Balance General'!D32)/'1. Balance General'!D32)*100 | E32: =(('1. Balance General'!F32-'1. Balance General'!E32)/'1. Balance General'!E32)*100 | F32: =(('1. Balance General'!G32-'1. Balance General'!F32)/'1. Balance General'!F32)*100
A33: Ganancias retenidas | B33: =(('1. Balance General'!C33-'1. Balance General'!B33)/'1. Balance General'!B33)*100 | C33: =(('1. Balance General'!D33-'1. Balance General'!C33)/'1. Balance General'!C33)*100 | D33: =(('1. Balance General'!E33-'1. Balance General'!D33)/'1. Balance General'!D33)*100 | E33: =(('1. Balance General'!F33-'1. Balance General'!E33)/'1. Balance General'!E33)*100 | F33: =(('1. Balance General'!G33-'1. Balance General'!F33)/'1. Balance General'!F33)*100
A34: Otro resultado integral | B34: =(('1. Balance General'!C34-'1. Balance General'!B34)/'1. Balance General'!B34)*100 | C34: =(('1. Balance General'!D34-'1. Balance General'!C34)/'1. Balance General'!C34)*100 | D34: =(('1. Balance General'!E34-'1. Balance General'!D34)/'1. Balance General'!D34)*100 | E34: =(('1. Balance General'!F34-'1. Balance General'!E34)/'1. Balance General'!E34)*100 | F34: =(('1. Balance General'!G34-'1. Balance General'!F34)/'1. Balance General'!F34)*100
A35: Resultado integral total periodo (Utilidad Neta) | B35: =(('1. Balance General'!C35-'1. Balance General'!B35)/'1. Balance General'!B35)*100 | C35: =(('1. Balance General'!D35-'1. Balance General'!C35)/'1. Balance General'!C35)*100 | D35: =(('1. Balance General'!E35-'1. Balance General'!D35)/'1. Balance General'!D35)*100 | E35: =(('1. Balance General'!F35-'1. Balance General'!E35)/'1. Balance General'!E35)*100 | F35: =(('1. Balance General'!G35-'1. Balance General'!F35)/'1. Balance General'!F35)*100
A36: Total Patrimonio de los Accionistas | B36: =(('1. Balance General'!C36-'1. Balance General'!B36)/'1. Balance General'!B36)*100 | C36: =(('1. Balance General'!D36-'1. Balance General'!C36)/'1. Balance General'!C36)*100 | D36: =(('1. Balance General'!E36-'1. Balance General'!D36)/'1. Balance General'!D36)*100 | E36: =(('1. Balance General'!F36-'1. Balance General'!E36)/'1. Balance General'!E36)*100 | F36: =(('1. Balance General'!G36-'1. Balance General'!F36)/'1. Balance General'!F36)*100
A38: PASIVOS NO CORRIENTES
A39: Operaciones de financiamiento | B39: =(('1. Balance General'!C39-'1. Balance General'!B39)/'1. Balance General'!B39)*100 | C39: =(('1. Balance General'!D39-'1. Balance General'!C39)/'1. Balance General'!C39)*100 | D39: =(('1. Balance General'!E39-'1. Balance General'!D39)/'1. Balance General'!D39)*100 | E39: =(('1. Balance General'!F39-'1. Balance General'!E39)/'1. Balance General'!E39)*100 | F39: =(('1. Balance General'!G39-'1. Balance General'!F39)/'1. Balance General'!F39)*100
A40: Obligaciones con vinculados | B40: =(('1. Balance General'!C40-'1. Balance General'!B40)/'1. Balance General'!B40)*100 | C40: =(('1. Balance General'!D40-'1. Balance General'!C40)/'1. Balance General'!C40)*100 | D40: =(('1. Balance General'!E40-'1. Balance General'!D40)/'1. Balance General'!D40)*100 | E40: =(('1. Balance General'!F40-'1. Balance General'!E40)/'1. Balance General'!E40)*100 | F40: =(('1. Balance General'!G40-'1. Balance General'!F40)/'1. Balance General'!F40)*100
A41: Operaciones con derivados | B41: =(('1. Balance General'!C41-'1. Balance General'!B41)/'1. Balance General'!B41)*100 | C41: =(('1. Balance General'!D41-'1. Balance General'!C41)/'1. Balance General'!C41)*100 | D41: =(('1. Balance General'!E41-'1. Balance General'!D41)/'1. Balance General'!D41)*100 | E41: =(('1. Balance General'!F41-'1. Balance General'!E41)/'1. Balance General'!E41)*100 | F41: =(('1. Balance General'!G41-'1. Balance General'!F41)/'1. Balance General'!F41)*100
A42: Impuestos, contribuciones y tasas | B42: =(('1. Balance General'!C42-'1. Balance General'!B42)/'1. Balance General'!B42)*100 | C42: =(('1. Balance General'!D42-'1. Balance General'!C42)/'1. Balance General'!C42)*100 | D42: =(('1. Balance General'!E42-'1. Balance General'!D42)/'1. Balance General'!D42)*100 | E42: =(('1. Balance General'!F42-'1. Balance General'!E42)/'1. Balance General'!E42)*100 | F42: =(('1. Balance General'!G42-'1. Balance General'!F42)/'1. Balance General'!F42)*100
A43: Beneficios a empleados | B43: =(('1. Balance General'!C43-'1. Balance General'!B43)/'1. Balance General'!B43)*100 | C43: =(('1. Balance General'!D43-'1. Balance General'!C43)/'1. Balance General'!C43)*100 | D43: =(('1. Balance General'!E43-'1. Balance General'!D43)/'1. Balance General'!D43)*100 | E43: =(('1. Balance General'!F43-'1. Balance General'!E43)/'1. Balance General'!E43)*100 | F43: =(('1. Balance General'!G43-'1. Balance General'!F43)/'1. Balance General'!F43)*100
A44: Provisiones | B44: =(('1. Balance General'!C44-'1. Balance General'!B44)/'1. Balance General'!B44)*100 | C44: =(('1. Balance General'!D44-'1. Balance General'!C44)/'1. Balance General'!C44)*100 | D44: =(('1. Balance General'!E44-'1. Balance General'!D44)/'1. Balance General'!D44)*100 | E44: =(('1. Balance General'!F44-'1. Balance General'!E44)/'1. Balance General'!E44)*100 | F44: =(('1. Balance General'!G44-'1. Balance General'!F44)/'1. Balance General'!F44)*100
A45: Cuentas por pagar | B45: =(('1. Balance General'!C45-'1. Balance General'!B45)/'1. Balance General'!B45)*100 | C45: =(('1. Balance General'!D45-'1. Balance General'!C45)/'1. Balance General'!C45)*100 | D45: =(('1. Balance General'!E45-'1. Balance General'!D45)/'1. Balance General'!D45)*100 | E45: =(('1. Balance General'!F45-'1. Balance General'!E45)/'1. Balance General'!E45)*100 | F45: =(('1. Balance General'!G45-'1. Balance General'!F45)/'1. Balance General'!F45)*100
A46: Total Pasivos No Corrientes | B46: =(('1. Balance General'!C46-'1. Balance General'!B46)/'1. Balance General'!B46)*100 | C46: =(('1. Balance General'!D46-'1. Balance General'!C46)/'1. Balance General'!C46)*100 | D46: =(('1. Balance General'!E46-'1. Balance General'!D46)/'1. Balance General'!D46)*100 | E46: =(('1. Balance General'!F46-'1. Balance General'!E46)/'1. Balance General'!E46)*100 | F46: =(('1. Balance General'!G46-'1. Balance General'!F46)/'1. Balance General'!F46)*100
A48: PASIVOS CORRIENTES
A49: Operaciones de financiamiento | B49: =(('1. Balance General'!C49-'1. Balance General'!B49)/'1. Balance General'!B49)*100 | C49: =(('1. Balance General'!D49-'1. Balance General'!C49)/'1. Balance General'!C49)*100 | D49: =(('1. Balance General'!E49-'1. Balance General'!D49)/'1. Balance General'!D49)*100 | E49: =(('1. Balance General'!F49-'1. Balance General'!E49)/'1. Balance General'!E49)*100 | F49: =(('1. Balance General'!G49-'1. Balance General'!F49)/'1. Balance General'!F49)*100
A50: Cuentas por pagar | B50: =(('1. Balance General'!C50-'1. Balance General'!B50)/'1. Balance General'!B50)*100 | C50: =(('1. Balance General'!D50-'1. Balance General'!C50)/'1. Balance General'!C50)*100 | D50: =(('1. Balance General'!E50-'1. Balance General'!D50)/'1. Balance General'!D50)*100 | E50: =(('1. Balance General'!F50-'1. Balance General'!E50)/'1. Balance General'!E50)*100 | F50: =(('1. Balance General'!G50-'1. Balance General'!F50)/'1. Balance General'!F50)*100
A51: Obligaciones con vinculados | B51: =(('1. Balance General'!C51-'1. Balance General'!B51)/'1. Balance General'!B51)*100 | C51: =(('1. Balance General'!D51-'1. Balance General'!C51)/'1. Balance General'!C51)*100 | D51: =(('1. Balance General'!E51-'1. Balance General'!D51)/'1. Balance General'!D51)*100 | E51: =(('1. Balance General'!F51-'1. Balance General'!E51)/'1. Balance General'!E51)*100 | F51: =(('1. Balance General'!G51-'1. Balance General'!F51)/'1. Balance General'!F51)*100
A52: Operaciones con derivados | B52: =(('1. Balance General'!C52-'1. Balance General'!B52)/'1. Balance General'!B52)*100 | C52: =(('1. Balance General'!D52-'1. Balance General'!C52)/'1. Balance General'!C52)*100 | D52: =(('1. Balance General'!E52-'1. Balance General'!D52)/'1. Balance General'!D52)*100 | E52: =(('1. Balance General'!F52-'1. Balance General'!E52)/'1. Balance General'!E52)*100 | F52: =(('1. Balance General'!G52-'1. Balance General'!F52)/'1. Balance General'!F52)*100
A53: Impuestos, contribuciones y tasas | B53: =(('1. Balance General'!C53-'1. Balance General'!B53)/'1. Balance General'!B53)*100 | C53: =(('1. Balance General'!D53-'1. Balance General'!C53)/'1. Balance General'!C53)*100 | D53: =(('1. Balance General'!E53-'1. Balance General'!D53)/'1. Balance General'!D53)*100 | E53: =(('1. Balance General'!F53-'1. Balance General'!E53)/'1. Balance General'!E53)*100 | F53: =(('1. Balance General'!G53-'1. Balance General'!F53)/'1. Balance General'!F53)*100
A54: Beneficios a empleados | B54: =(('1. Balance General'!C54-'1. Balance General'!B54)/'1. Balance General'!B54)*100 | C54: =(('1. Balance General'!D54-'1. Balance General'!C54)/'1. Balance General'!C54)*100 | D54: =(('1. Balance General'!E54-'1. Balance General'!D54)/'1. Balance General'!D54)*100 | E54: =(('1. Balance General'!F54-'1. Balance General'!E54)/'1. Balance General'!E54)*100 | F54: =(('1. Balance General'!G54-'1. Balance General'!F54)/'1. Balance General'!F54)*100
A55: Provisiones | B55: =(('1. Balance General'!C55-'1. Balance General'!B55)/'1. Balance General'!B55)*100 | C55: =(('1. Balance General'!D55-'1. Balance General'!C55)/'1. Balance General'!C55)*100 | D55: =(('1. Balance General'!E55-'1. Balance General'!D55)/'1. Balance General'!D55)*100 | E55: =(('1. Balance General'!F55-'1. Balance General'!E55)/'1. Balance General'!E55)*100 | F55: =(('1. Balance General'!G55-'1. Balance General'!F55)/'1. Balance General'!F55)*100
A56: Otros pasivos | B56: =(('1. Balance General'!C56-'1. Balance General'!B56)/'1. Balance General'!B56)*100 | C56: =(('1. Balance General'!D56-'1. Balance General'!C56)/'1. Balance General'!C56)*100 | D56: =(('1. Balance General'!E56-'1. Balance General'!D56)/'1. Balance General'!D56)*100 | E56: =(('1. Balance General'!F56-'1. Balance General'!E56)/'1. Balance General'!E56)*100 | F56: =(('1. Balance General'!G56-'1. Balance General'!F56)/'1. Balance General'!F56)*100

Sheet 5. Análisis Vertical ER
A1: ISAGEN S.A. E.S.P.
A2: ANÁLISIS VERTICAL - ESTADO DE RESULTADOS
A3: Composición porcentual respecto a Ingresos (%)
A5: CONCEPTO | B5: 2020 | C5: 2021 | D5: 2022 | E5: 2023 | F5: 2024 | G5: 2025 (9m)
A6: Ingresos de contratos con clientes | B6: =('2. Estado de Resultados'!B6/'2. Estado de Resultados'!B6)*100 | C6: =('2. Estado de Resultados'!C6/'2. Estado de Resultados'!C6)*100 | D6: =('2. Estado de Resultados'!D6/'2. Estado de Resultados'!D6)*100 | E6: =('2. Estado de Resultados'!E6/'2. Estado de Resultados'!E6)*100 | F6: =('2. Estado de Resultados'!F6/'2. Estado de Resultados'!F6)*100 | G6: =('2. Estado de Resultados'!G6/'2. Estado de Resultados'!G6)*100
A7: Costo de ventas | B7: =('2. Estado de Resultados'!B7/'2. Estado de Resultados'!B6)*100 | C7: =('2. Estado de Resultados'!C7/'2. Estado de Resultados'!C6)*100 | D7: =('2. Estado de Resultados'!D7/'2. Estado de Resultados'!D6)*100 | E7: =('2. Estado de Resultados'!E7/'2. Estado de Resultados'!E6)*100 | F7: =('2. Estado de Resultados'!F7/'2. Estado de Resultados'!F6)*100 | G7: =('2. Estado de Resultados'!G7/'2. Estado de Resultados'!G6)*100
A8: Utilidad Bruta | B8: =('2. Estado de Resultados'!B8/'2. Estado de Resultados'!B6)*100 | C8: =('2. Estado de Resultados'!C8/'2. Estado de Resultados'!C6)*100 | D8: =('2. Estado de Resultados'!D8/'2. Estado de Resultados'!D6)*100 | E8: =('2. Estado de Resultados'!E8/'2. Estado de Resultados'!E6)*100 | F8: =('2. Estado de Resultados'!F8/'2. Estado de Resultados'!F6)*100 | G8: =('2. Estado de Resultados'!G8/'2. Estado de Resultados'!G6)*100
A9: Otros ingresos | B9: =('2. Estado de Resultados'!B9/'2. Estado de Resultados'!B6)*100 | C9: =('2. Estado de Resultados'!C9/'2. Estado de Resultados'!C6)*100 | D9: =('2. Estado de Resultados'!D9/'2. Estado de Resultados'!D6)*100 | E9: =('2. Estado de Resultados'!E9/'2. Estado de Resultados'!E6)*100 | F9: =('2. Estado de Resultados'!F9/'2. Estado de Resultados'!F6)*100 | G9: =('2. Estado de Resultados'!G9/'2. Estado de Resultados'!G6)*100
A10: Gastos de administración | B10: =('2. Estado de Resultados'!B10/'2. Estado de Resultados'!B6)*100 | C10: =('2. Estado de Resultados'!C10/'2. Estado de Resultados'!C6)*100 | D10: =('2. Estado de Resultados'!D10/'2. Estado de Resultados'!D6)*100 | E10: =('2. Estado de Resultados'!E10/'2. Estado de Resultados'!E6)*100 | F10: =('2. Estado de Resultados'!F10/'2. Estado de Resultados'!F6)*100 | G10: =('2. Estado de Resultados'!G10/'2. Estado de Resultados'!G6)*100
A11: Otros gastos | B11: =('2. Estado de Resultados'!B11/'2. Estado de Resultados'!B6)*100 | C11: =('2. Estado de Resultados'!C11/'2. Estado de Resultados'!C6)*100 | D11: =('2. Estado de Resultados'!D11/'2. Estado de Resultados'!D6)*100 | E11: =('2. Estado de Resultados'!E11/'2. Estado de Resultados'!E6)*100 | F11: =('2. Estado de Resultados'!F11/'2. Estado de Resultados'!F6)*100 | G11: =('2. Estado de Resultados'!G11/'2. Estado de Resultados'!G6)*100
A12: Ingresos financieros | B12: =('2. Estado de Resultados'!B12/'2. Estado de Resultados'!B6)*100 | C12: =('2. Estado de Resultados'!C12/'2. Estado de Resultados'!C6)*100 | D12: =('2. Estado de Resultados'!D12/'2. Estado de Resultados'!D6)*100 | E12: =('2. Estado de Resultados'!E12/'2. Estado de Resultados'!E6)*100 | F12: =('2. Estado de Resultados'!F12/'2. Estado de Resultados'!F6)*100 | G12: =('2. Estado de Resultados'!G12/'2. Estado de Resultados'!G6)*100
A13: Gastos financieros | B13: =('2. Estado de Resultados'!B13/'2. Estado de Resultados'!B6)*100 | C13: =('2. Estado de Resultados'!C13/'2. Estado de Resultados'!C6)*100 | D13: =('2. Estado de Resultados'!D13/'2. Estado de Resultados'!D6)*100 | E13: =('2. Estado de Resultados'!E13/'2. Estado de Resultados'!E6)*100 | F13: =('2. Estado de Resultados'!F13/'2. Estado de Resultados'!F6)*100 | G13: =('2. Estado de Resultados'!G13/'2. Estado de Resultados'!G6)*100
A14: Diferencia en cambio, neta | B14: =('2. Estado de Resultados'!B14/'2. Estado de Resultados'!B6)*100 | C14: =('2. Estado de Resultados'!C14/'2. Estado de Resultados'!C6)*100 | D14: =('2. Estado de Resultados'!D14/'2. Estado de Resultados'!D6)*100 | E14: =('2. Estado de Resultados'!E14/'2. Estado de Resultados'!E6)*100 | F14: =('2. Estado de Resultados'!F14/'2. Estado de Resultados'!F6)*100 | G14: =('2. Estado de Resultados'!G14/'2. Estado de Resultados'!G6)*100
A15: Utilidad Antes de Impuestos | B15: =('2. Estado de Resultados'!B15/'2. Estado de Resultados'!B6)*100 | C15: =('2. Estado de Resultados'!C15/'2. Estado de Resultados'!C6)*100 | D15: =('2. Estado de Resultados'!D15/'2. Estado de Resultados'!D6)*100 | E15: =('2. Estado de Resultados'!E15/'2. Estado de Resultados'!E6)*100 | F15: =('2. Estado de Resultados'!F15/'2. Estado de Resultados'!F6)*100 | G15: =('2. Estado de Resultados'!G15/'2. Estado de Resultados'!G6)*100
A16: EBIT | B16: =('2. Estado de Resultados'!B16/'2. Estado de Resultados'!B6)*100 | C16: =('2. Estado de Resultados'!C16/'2. Estado de Resultados'!C6)*100 | D16: =('2. Estado de Resultados'!D16/'2. Estado de Resultados'!D6)*100 | E16: =('2. Estado de Resultados'!E16/'2. Estado de Resultados'!E6)*100 | F16: =('2. Estado de Resultados'!F16/'2. Estado de Resultados'!F6)*100 | G16: =('2. Estado de Resultados'!G16/'2. Estado de Resultados'!G6)*100
A17: Depreciación | B17: =('2. Estado de Resultados'!B17/'2. Estado de Resultados'!B6)*100 | C17: =('2. Estado de Resultados'!C17/'2. Estado de Resultados'!C6)*100 | D17: =('2. Estado de Resultados'!D17/'2. Estado de Resultados'!D6)*100 | E17: =('2. Estado de Resultados'!E17/'2. Estado de Resultados'!E6)*100 | F17: =('2. Estado de Resultados'!F17/'2. Estado de Resultados'!F6)*100 | G17: =('2. Estado de Resultados'!G17/'2. Estado de Resultados'!G6)*100
A18: Amortización | B18: =('2. Estado de Resultados'!B18/'2. Estado de Resultados'!B6)*100 | C18: =('2. Estado de Resultados'!C18/'2. Estado de Resultados'!C6)*100 | D18: =('2. Estado de Resultados'!D18/'2. Estado de Resultados'!D6)*100 | E18: =('2. Estado de Resultados'!E18/'2. Estado de Resultados'!E6)*100 | F18: =('2. Estado de Resultados'!F18/'2. Estado de Resultados'!F6)*100 | G18: =('2. Estado de Resultados'!G18/'2. Estado de Resultados'!G6)*100
A19: EBITDA | B19: =('2. Estado de Resultados'!B19/'2. Estado de Resultados'!B6)*100 | C19: =('2. Estado de Resultados'!C19/'2. Estado de Resultados'!C6)*100 | D19: =('2. Estado de Resultados'!D19/'2. Estado de Resultados'!D6)*100 | E19: =('2. Estado de Resultados'!E19/'2. Estado de Resultados'!E6)*100 | F19: =('2. Estado de Resultados'!F19/'2. Estado de Resultados'!F6)*100 | G19: =('2. Estado de Resultados'!G19/'2. Estado de Resultados'!G6)*100
A20: Impuesto de renta - Corriente | B20: =('2. Estado de Resultados'!B20/'2. Estado de Resultados'!B6)*100 | C20: =('2. Estado de Resultados'!C20/'2. Estado de Resultados'!C6)*100 | D20: =('2. Estado de Resultados'!D20/'2. Estado de Resultados'!D6)*100 | E20: =('2. Estado de Resultados'!E20/'2. Estado de Resultados'!E6)*100 | F20: =('2. Estado de Resultados'!F20/'2. Estado de Resultados'!F6)*100 | G20: =('2. Estado de Resultados'!G20/'2. Estado de Resultados'!G6)*100
A21: Impuesto de renta - Diferido | B21: =('2. Estado de Resultados'!B21/'2. Estado de Resultados'!B6)*100 | C21: =('2. Estado de Resultados'!C21/'2. Estado de Resultados'!C6)*100 | D21: =('2. Estado de Resultados'!D21/'2. Estado de Resultados'!D6)*100 | E21: =('2. Estado de Resultados'!E21/'2. Estado de Resultados'!E6)*100 | F21: =('2. Estado de Resultados'!F21/'2. Estado de Resultados'!F6)*100 | G21: =('2. Estado de Resultados'!G21/'2. Estado de Resultados'!G6)*100
A22: Utilidad Neta del Periodo | B22: =('2. Estado de Resultados'!B22/'2. Estado de Resultados'!B6)*100 | C22: =('2. Estado de Resultados'!C22/'2. Estado de Resultados'!C6)*100 | D22: =('2. Estado de Resultados'!D22/'2. Estado de Resultados'!D6)*100 | E22: =('2. Estado de Resultados'!E22/'2. Estado de Resultados'!E6)*100 | F22: =('2. Estado de Resultados'!F22/'2. Estado de Resultados'!F6)*100 | G22: =('2. Estado de Resultados'!G22/'2. Estado de Resultados'!G6)*100
A25: OTRO RESULTADO INTEGRAL (ORI)
A26: Ganancias actuariales (Beneficios definidos) | B26: =('2. Estado de Resultados'!B26/'2. Estado de Resultados'!B6)*100 | C26: =('2. Estado de Resultados'!C26/'2. Estado de Resultados'!C6)*100 | D26: =('2. Estado de Resultados'!D26/'2. Estado de Resultados'!D6)*100 | E26: =('2. Estado de Resultados'!E26/'2. Estado de Resultados'!E6)*100 | F26: =('2. Estado de Resultados'!F26/'2. Estado de Resultados'!F6)*100 | G26: =('2. Estado de Resultados'!G26/'2. Estado de Resultados'!G6)*100
A27: Coberturas flujo de efectivo | B27: =('2. Estado de Resultados'!B27/'2. Estado de Resultados'!B6)*100 | C27: =('2. Estado de Resultados'!C27/'2. Estado de Resultados'!C6)*100 | D27: =('2. Estado de Resultados'!D27/'2. Estado de Resultados'!D6)*100 | E27: =('2. Estado de Resultados'!E27/'2. Estado de Resultados'!E6)*100 | F27: =('2. Estado de Resultados'!F27/'2. Estado de Resultados'!F6)*100 | G27: =('2. Estado de Resultados'!G27/'2. Estado de Resultados'!G6)*100
A28: Total Otro Resultado Integral, neto | B28: =('2. Estado de Resultados'!B28/'2. Estado de Resultados'!B6)*100 | C28: =('2. Estado de Resultados'!C28/'2. Estado de Resultados'!C6)*100 | D28: =('2. Estado de Resultados'!D28/'2. Estado de Resultados'!D6)*100 | E28: =('2. Estado de Resultados'!E28/'2. Estado de Resultados'!E6)*100 | F28: =('2. Estado de Resultados'!F28/'2. Estado de Resultados'!F6)*100 | G28: =('2. Estado de Resultados'!G28/'2. Estado de Resultados'!G6)*100
A29: RESULTADO INTEGRAL TOTAL | B29: =('2. Estado de Resultados'!B29/'2. Estado de Resultados'!B6)*100 | C29: =('2. Estado de Resultados'!C29/'2. Estado de Resultados'!C6)*100 | D29: =('2. Estado de Resultados'!D29/'2. Estado de Resultados'!D6)*100 | E29: =('2. Estado de Resultados'!E29/'2. Estado de Resultados'!E6)*100 | F29: =('2. Estado de Resultados'!F29/'2. Estado de Resultados'!F6)*100 | G29: =('2. Estado de Resultados'!G29/'2. Estado de Resultados'!G6)*100
A31: Utilidad básica y diluida por acción ($) | B31: =('2. Estado de Resultados'!B31/'2. Estado de Resultados'!B6)*100 | C31: =('2. Estado de Resultados'!C31/'2. Estado de Resultados'!C6)*100 | D31: =('2. Estado de Resultados'!D31/'2. Estado de Resultados'!D6)*100 | E31: =('2. Estado de Resultados'!E31/'2. Estado de Resultados'!E6)*100 | F31: =('2. Estado de Resultados'!F31/'2. Estado de Resultados'!F6)*100 | G31: =('2. Estado de Resultados'!G31/'2. Estado de Resultados'!G6)*100

Sheet 6. Análisis Horizontal ER
A1: ISAGEN S.A. E.S.P.
A2: ANÁLISIS HORIZONTAL - ESTADO DE RESULTADOS
A3: Variación porcentual interanual (%)
A5: CONCEPTO | B5: 2020-2021 | C5: 2021-2022 | D5: 2022-2023 | E5: 2023-2024 | F5: 2024-2025
A6: Ingresos de contratos con clientes | B6: =(('2. Estado de Resultados'!C6-'2. Estado de Resultados'!B6)/'2. Estado de Resultados'!B6)*100 | C6: =(('2. Estado de Resultados'!D6-'2. Estado de Resultados'!C6)/'2. Estado de Resultados'!C6)*100 | D6: =(('2. Estado de Resultados'!E6-'2. Estado de Resultados'!D6)/'2. Estado de Resultados'!D6)*100 | E6: =(('2. Estado de Resultados'!F6-'2. Estado de Resultados'!E6)/'2. Estado de Resultados'!E6)*100 | F6: =(('2. Estado de Resultados'!G6-'2. Estado de Resultados'!F6)/'2. Estado de Resultados'!F6)*100
A7: Costo de ventas | B7: =(('2. Estado de Resultados'!C7-'2. Estado de Resultados'!B7)/'2. Estado de Resultados'!B7)*100 | C7: =(('2. Estado de Resultados'!D7-'2. Estado de Resultados'!C7)/'2. Estado de Resultados'!C7)*100 | D7: =(('2. Estado de Resultados'!E7-'2. Estado de Resultados'!D7)/'2. Estado de Resultados'!D7)*100 | E7: =(('2. Estado de Resultados'!F7-'2. Estado de Resultados'!E7)/'2. Estado de Resultados'!E7)*100 | F7: =(('2. Estado de Resultados'!G7-'2. Estado de Resultados'!F7)/'2. Estado de Resultados'!F7)*100
A8: Utilidad Bruta | B8: =(('2. Estado de Resultados'!C8-'2. Estado de Resultados'!B8)/'2. Estado de Resultados'!B8)*100 | C8: =(('2. Estado de Resultados'!D8-'2. Estado de Resultados'!C8)/'2. Estado de Resultados'!C8)*100 | D8: =(('2. Estado de Resultados'!E8-'2. Estado de Resultados'!D8)/'2. Estado de Resultados'!D8)*100 | E8: =(('2. Estado de Resultados'!F8-'2. Estado de Resultados'!E8)/'2. Estado de Resultados'!E8)*100 | F8: =(('2. Estado de Resultados'!G8-'2. Estado de Resultados'!F8)/'2. Estado de Resultados'!F8)*100
A9: Otros ingresos | B9: =(('2. Estado de Resultados'!C9-'2. Estado de Resultados'!B9)/'2. Estado de Resultados'!B9)*100 | C9: =(('2. Estado de Resultados'!D9-'2. Estado de Resultados'!C9)/'2. Estado de Resultados'!C9)*100 | D9: =(('2. Estado de Resultados'!E9-'2. Estado de Resultados'!D9)/'2. Estado de Resultados'!D9)*100 | E9: =(('2. Estado de Resultados'!F9-'2. Estado de Resultados'!E9)/'2. Estado de Resultados'!E9)*100 | F9: =(('2. Estado de Resultados'!G9-'2. Estado de Resultados'!F9)/'2. Estado de Resultados'!F9)*100
A10: Gastos de administración | B10: =(('2. Estado de Resultados'!C10-'2. Estado de Resultados'!B10)/'2. Estado de Resultados'!B10)*100 | C10: =(('2. Estado de Resultados'!D10-'2. Estado de Resultados'!C10)/'2. Estado de Resultados'!C10)*100 | D10: =(('2. Estado de Resultados'!E10-'2. Estado de Resultados'!D10)/'2. Estado de Resultados'!D10)*100 | E10: =(('2. Estado de Resultados'!F10-'2. Estado de Resultados'!E10)/'2. Estado de Resultados'!E10)*100 | F10: =(('2. Estado de Resultados'!G10-'2. Estado de Resultados'!F10)/'2. Estado de Resultados'!F10)*100
A11: Otros gastos | B11: =(('2. Estado de Resultados'!C11-'2. Estado de Resultados'!B11)/'2. Estado de Resultados'!B11)*100 | C11: =(('2. Estado de Resultados'!D11-'2. Estado de Resultados'!C11)/'2. Estado de Resultados'!C11)*100 | D11: =(('2. Estado de Resultados'!E11-'2. Estado de Resultados'!D11)/'2. Estado de Resultados'!D11)*100 | E11: =(('2. Estado de Resultados'!F11-'2. Estado de Resultados'!E11)/'2. Estado de Resultados'!E11)*100 | F11: =(('2. Estado de Resultados'!G11-'2. Estado de Resultados'!F11)/'2. Estado de Resultados'!F11)*100
A12: Ingresos financieros | B12: =(('2. Estado de Resultados'!C12-'2. Estado de Resultados'!B12)/'2. Estado de Resultados'!B12)*100 | C12: =(('2. Estado de Resultados'!D12-'2. Estado de Resultados'!C12)/'2. Estado de Resultados'!C12)*100 | D12: =(('2. Estado de Resultados'!E12-'2. Estado de Resultados'!D12)/'2. Estado de Resultados'!D12)*100 | E12: =(('2. Estado de Resultados'!F12-'2. Estado de Resultados'!E12)/'2. Estado de Resultados'!E12)*100 | F12: =(('2. Estado de Resultados'!G12-'2. Estado de Resultados'!F12)/'2. Estado de Resultados'!F12)*100
A13: Gastos financieros | B13: =(('2. Estado de Resultados'!C13-'2. Estado de Resultados'!B13)/'2. Estado de Resultados'!B13)*100 | C13: =(('2. Estado de Resultados'!D13-'2. Estado de Resultados'!C13)/'2. Estado de Resultados'!C13)*100 | D13: =(('2. Estado de Resultados'!E13-'2. Estado de Resultados'!D13)/'2. Estado de Resultados'!D13)*100 | E13: =(('2. Estado de Resultados'!F13-'2. Estado de Resultados'!E13)/'2. Estado de Resultados'!E13)*100 | F13: =(('2. Estado de Resultados'!G13-'2. Estado de Resultados'!F13)/'2. Estado de Resultados'!F13)*100
A14: Diferencia en cambio, neta | B14: =(('2. Estado de Resultados'!C14-'2. Estado de Resultados'!B14)/'2. Estado de Resultados'!B14)*100 | C14: =(('2. Estado de Resultados'!D14-'2. Estado de Resultados'!C14)/'2. Estado de Resultados'!C14)*100 | D14: =(('2. Estado de Resultados'!E14-'2. Estado de Resultados'!D14)/'2. Estado de Resultados'!D14)*100 | E14: =(('2. Estado de Resultados'!F14-'2. Estado de Resultados'!E14)/'2. Estado de Resultados'!E14)*100 | F14: =(('2. Estado de Resultados'!G14-'2. Estado de Resultados'!F14)/'2. Estado de Resultados'!F14)*100
A15: Utilidad Antes de Impuestos | B15: =(('2. Estado de Resultados'!C15-'2. Estado de Resultados'!B15)/'2. Estado de Resultados'!B15)*100 | C15: =(('2. Estado de Resultados'!D15-'2. Estado de Resultados'!C15)/'2. Estado de Resultados'!C15)*100 | D15: =(('2. Estado de Resultados'!E15-'2. Estado de Resultados'!D15)/'2. Estado de Resultados'!D15)*100 | E15: =(('2. Estado de Resultados'!F15-'2. Estado de Resultados'!E15)/'2. Estado de Resultados'!E15)*100 | F15: =(('2. Estado de Resultados'!G15-'2. Estado de Resultados'!F15)/'2. Estado de Resultados'!F15)*100
A16: EBIT | B16: =(('2. Estado de Resultados'!C16-'2. Estado de Resultados'!B16)/'2. Estado de Resultados'!B16)*100 | C16: =(('2. Estado de Resultados'!D16-'2. Estado de Resultados'!C16)/'2. Estado de Resultados'!C16)*100 | D16: =(('2. Estado de Resultados'!E16-'2. Estado de Resultados'!D16)/'2. Estado de Resultados'!D16)*100 | E16: =(('2. Estado de Resultados'!F16-'2. Estado de Resultados'!E16)/'2. Estado de Resultados'!E16)*100 | F16: =(('2. Estado de Resultados'!G16-'2. Estado de Resultados'!F16)/'2. Estado de Resultados'!F16)*100
A17: Depreciación | B17: =(('2. Estado de Resultados'!C17-'2. Estado de Resultados'!B17)/'2. Estado de Resultados'!B17)*100 | C17: =(('2. Estado de Resultados'!D17-'2. Estado de Resultados'!C17)/'2. Estado de Resultados'!C17)*100 | D17: =(('2. Estado de Resultados'!E17-'2. Estado de Resultados'!D17)/'2. Estado de Resultados'!D17)*100 | E17: =(('2. Estado de Resultados'!F17-'2. Estado de Resultados'!E17)/'2. Estado de Resultados'!E17)*100 | F17: =(('2. Estado de Resultados'!G17-'2. Estado de Resultados'!F17)/'2. Estado de Resultados'!F17)*100
... A22: Utilidad Neta del Periodo | B22: =(('2. Estado de Resultados'!C22-'2. Estado de Resultados'!B22)/'2. Estado de Resultados'!B22)*100 | C22: =(('2. Estado de Resultados'!D22-'2. Estado de Resultados'!C22)/'2. Estado de Resultados'!C22)*100 | D22: =(('2. Estado de Resultados'!E22-'2. Estado de Resultados'!D22)/'2. Estado de Resultados'!D22)*100 | E22: =(('2. Estado de Resultados'!F22-'2. Estado de Resultados'!E22)/'2. Estado de Resultados'!E22)*100 | F22: =(('2. Estado de Resultados'!G22-'2. Estado de Resultados'!F22)/'2. Estado de Resultados'!F22)*100
A25: OTRO RESULTADO INTEGRAL (ORI)
A26: Ganancias actuariales (Beneficios definidos) | B26: =(('2. Estado de Resultados'!C26-'2. Estado de Resultados'!B26)/'2. Estado de Resultados'!B26)*100 | C26: =(('2. Estado de Resultados'!D26-'2. Estado de Resultados'!C26)/'2. Estado de Resultados'!C26)*100 | D26: =(('2. Estado de Resultados'!E26-'2. Estado de Resultados'!D26)/'2. Estado de Resultados'!D26)*100 | E26: =(('2. Estado de Resultados'!F26-'2. Estado de Resultados'!E26)/'2. Estado de Resultados'!E26)*100 | F26: =(('2. Estado de Resultados'!G26-'2. Estado de Resultados'!F26)/'2. Estado de Resultados'!F26)*100
A27: Coberturas flujo de efectivo | B27: =(('2. Estado de Resultados'!C27-'2. Estado de Resultados'!B27)/'2. Estado de Resultados'!B27)*100 | C27: =(('2. Estado de Resultados'!D27-'2. Estado de Resultados'!C27)/'2. Estado de Resultados'!C27)*100 | D27: =(('2. Estado de Resultados'!E27-'2. Estado de Resultados'!D27)/'2. Estado de Resultados'!D27)*100 | E27: =(('2. Estado de Resultados'!F27-'2. Estado de Resultados'!E27)/'2. Estado de Resultados'!E27)*100 | F27: =(('2. Estado de Resultados'!G27-'2. Estado de Resultados'!F27)/'2. Estado de Resultados'!F27)*100
A28: Total Otro Resultado Integral, neto | B28: =(('2. Estado de Resultados'!C28-'2. Estado de Resultados'!B28)/'2. Estado de Resultados'!B28)*100 | C28: =(('2. Estado de Resultados'!D28-'2. Estado de Resultados'!C28)/'2. Estado de Resultados'!C28)*100 | D28: =(('2. Estado de Resultados'!E28-'2. Estado de Resultados'!D28)/'2. Estado de Resultados'!D28)*100 | E28: =(('2. Estado de Resultados'!F28-'2. Estado de Resultados'!E28)/'2. Estado de Resultados'!E28)*100 | F28: =(('2. Estado de Resultados'!G28-'2. Estado de Resultados'!F28)/'2. Estado de Resultados'!F28)*100
A29: RESULTADO INTEGRAL TOTAL | B29: =(('2. Estado de Resultados'!C29-'2. Estado de Resultados'!B29)/'2. Estado de Resultados'!B29)*100 | C29: =(('2. Estado de Resultados'!D29-'2. Estado de Resultados'!C29)/'2. Estado de Resultados'!C29)*100 | D29: =(('2. Estado de Resultados'!E29-'2. Estado de Resultados'!D29)/'2. Estado de Resultados'!D29)*100 | E29: =(('2. Estado de Resultados'!F29-'2. Estado de Resultados'!E29)/'2. Estado de Resultados'!E29)*100 | F29: =(('2. Estado de Resultados'!G29-'2. Estado de Resultados'!F29)/'2. Estado de Resultados'!F29)*100
A31: Utilidad básica y diluida por acción ($) | B31: =(('2. Estado de Resultados'!C31-'2. Estado de Resultados'!B31)/'2. Estado de Resultados'!B31)*100 | C31: =(('2. Estado de Resultados'!D31-'2. Estado de Resultados'!C31)/'2. Estado de Resultados'!C31)*100 | D31: =(('2. Estado de Resultados'!E31-'2. Estado de Resultados'!D31)/'2. Estado de Resultados'!D31)*100 | E31: =(('2. Estado de Resultados'!F31-'2. Estado de Resultados'!E31)/'2. Estado de Resultados'!E31)*100 | F31: =(('2. Estado de Resultados'!G31-'2. Estado de Resultados'!F31)/'2. Estado de Resultados'!F31)*100

Sheet 7. Indicadores Financieros
A1: ISAGEN S.A. E.S.P.
A2: INDICADORES FINANCIEROS CLAVE
A3: Valores en millones de pesos colombianos (COP)
A5: INDICADOR | B5: 2020 | C5: 2021 | D5: 2022 | E5: 2023 | F5: 2024 | G5: 2025 (Sep)
A6: EBITDA | B6: ='2. Estado de Resultados'!B19 | C6: ='2. Estado de Resultados'!C19 | D6: ='2. Estado de Resultados'!D19 | E6: ='2. Estado de Resultados'!E19 | F6: ='2. Estado de Resultados'!F19 | G6: ='2. Estado de Resultados'!G19
A8: CAPITAL DE TRABAJO NETO OPERATIVO (KTNO)
A9: Activos Corrientes Operativos | B9: ='1. Balance General'!B25-'1. Balance General'!B24-'1. Balance General'!B23 | C9: ='1. Balance General'!C25-'1. Balance General'!C24-'1. Balance General'!C23 | D9: ='1. Balance General'!D25-'1. Balance General'!D24-'1. Balance General'!D23 | E9: ='1. Balance General'!E25-'1. Balance General'!E24-'1. Balance General'!E23 | F9: ='1. Balance General'!F25-'1. Balance General'!F24-'1. Balance General'!F23 | G9: ='1. Balance General'!G25-'1. Balance General'!G24-'1. Balance General'!G23
A10: Pasivos Corrientes Operativos | B10: ='1. Balance General'!B57-'1. Balance General'!B49-'1. Balance General'!B52-'1. Balance General'!B51 | C10: ='1. Balance General'!C57-'1. Balance General'!C49-'1. Balance General'!C52-'1. Balance General'!C51 | D10: ='1. Balance General'!D57-'1. Balance General'!D49-'1. Balance General'!D52-'1. Balance General'!D51 | E10: ='1. Balance General'!E57-'1. Balance General'!E49-'1. Balance General'!E52-'1. Balance General'!E51 | F10: ='1. Balance General'!F57-'1. Balance General'!F49-'1. Balance General'!F52-'1. Balance General'!F51 | G10: ='1. Balance General'!G57-'1. Balance General'!G49-'1. Balance General'!G52-'1. Balance General'!G51
A11: KTNO | B11: =B9-B10 | C11: =C9-C10 | D11: =D9-D10 | E11: =E9-E10 | F11: =F9-F10 | G11: =G9-G10
A13: ΔKTNO (Variación del KTNO) | B13: N/A | C13: =C11-B11 | D13: =D11-C11 | E13: =E11-D11 | F13: =F11-E11 | G13: =G11-F11
A15: ANDEO (Activos Netos de Operación) | B15: ='1. Balance General'!B27-'1. Balance General'!B50+'1. Balance General'!B52+'1. Balance General'!B53+'1. Balance General'!B54+'1. Balance General'!B55+'1. Balance General'!B56 | C15: ='1. Balance General'!C27-'1. Balance General'!C50+'1. Balance General'!C52+'1. Balance General'!C53+'1. Balance General'!C54+'1. Balance General'!C55+'1. Balance General'!C56 | D15: ='1. Balance General'!D27-'1. Balance General'!D50+'1. Balance General'!D52+'1. Balance General'!D53+'1. Balance General'!D54+'1. Balance General'!D55+'1. Balance General'!D56 | E15: ='1. Balance General'!E27-'1. Balance General'!E50+'1. Balance General'!E52+'1. Balance General'!E53+'1. Balance General'!E54+'1. Balance General'!E55+'1. Balance General'!E56 | F15: ='1. Balance General'!F27-'1. Balance General'!F50+'1. Balance General'!F52+'1. Balance General'!F53+'1. Balance General'!F54+'1. Balance General'!F55+'1. Balance General'!F56 | G15: ='1. Balance General'!G27-'1. Balance General'!G50+'1. Balance General'!G52+'1. Balance General'!G53+'1. Balance General'!G54+'1. Balance General'!G55+'1. Balance General'!G56
A17: CICLO DE CONVERSIÓN DE EFECTIVO (CCE)
A18: Días de Inventario | B18: =(('1. Balance General'!B17/ABS('2. Estado de Resultados'!B7))*365) | C18: =(('1. Balance General'!C17/ABS('2. Estado de Resultados'!C7))*365) | D18: =(('1. Balance General'!D17/ABS('2. Estado de Resultados'!D7))*365) | E18: =(('1. Balance General'!E17/ABS('2. Estado de Resultados'!E7))*365) | F18: =(('1. Balance General'!F17/ABS('2. Estado de Resultados'!F7))*365) | G18: =(('1. Balance General'!G17/ABS('2. Estado de Resultados'!G7))*365)
A19: Días de Cartera (CxC) | B19: =(('1. Balance General'!B18/'2. Estado de Resultados'!B6)*365) | C19: =(('1. Balance General'!C18/'2. Estado de Resultados'!C6)*365) | D19: =(('1. Balance General'!D18/'2. Estado de Resultados'!D6)*365) | E19: =(('1. Balance General'!E18/'2. Estado de Resultados'!E6)*365) | F19: =(('1. Balance General'!F18/'2. Estado de Resultados'!F6)*365) | G19: =(('1. Balance General'!G18/'2. Estado de Resultados'!G6)*365)
A20: Días de Proveedores (CxP) | B20: =(('1. Balance General'!B50/ABS('2. Estado de Resultados'!B7))*365) | C20: =(('1. Balance General'!C50/ABS('2. Estado de Resultados'!C7))*365) | D20: =(('1. Balance General'!D50/ABS('2. Estado de Resultados'!D7))*365) | E20: =(('1. Balance General'!E50/ABS('2. Estado de Resultados'!E7))*365) | F20: =(('1. Balance General'!F50/ABS('2. Estado de Resultados'!F7))*365) | G20: =(('1. Balance General'!G50/ABS('2. Estado de Resultados'!G7))*365)
A21: CCE (días) | B21: =B18+B19-B20 | C21: =C18+C19-C20 | D21: =D18+D19-D20 | E21: =E18+E19-E20 | F21: =F18+F19-F20 | G21: =G18+G19-G20
A23: PKT - Productividad del Capital de Trabajo | B23: ='2. Estado de Resultados'!B6/B11 | C23: ='2. Estado de Resultados'!C6/C11 | D23: ='2. Estado de Resultados'!D6/D11 | E23: ='2. Estado de Resultados'!E6/E11 | F23: ='2. Estado de Resultados'!F6/F11 | G23: ='2. Estado de Resultados'!G6/G11

Sheet 8. Flujos de Caja
A1: ISAGEN S.A. E.S.P.
A2: FLUJOS DE CAJA
A3: Valores en millones de pesos colombianos (COP)
A5: CONCEPTO | B5: 2020 | C5: 2021 | D5: 2022 | E5: 2023 | F5: 2024 | G5: 2025 (Sep)
A6: A. FLUJO DE CAJA OPERACIONAL (FCO)
A7: EBITDA | B7: ='7. Indicadores Financieros'!B6 | C7: ='7. Indicadores Financieros'!C6 | D7: ='7. Indicadores Financieros'!D6 | E7: ='7. Indicadores Financieros'!E6 | F7: ='7. Indicadores Financieros'!F6 | G7: ='7. Indicadores Financieros'!G6
A8: (-) Impuesto de Renta Total | B8: ='2. Estado de Resultados'!B20+'2. Estado de Resultados'!B21 | C8: ='2. Estado de Resultados'!C20+'2. Estado de Resultados'!C21 | D8: ='2. Estado de Resultados'!D20+'2. Estado de Resultados'!D21 | E8: ='2. Estado de Resultados'!E20+'2. Estado de Resultados'!E21 | F8: ='2. Estado de Resultados'!F20+'2. Estado de Resultados'!F21 | G8: ='2. Estado de Resultados'!G20+'2. Estado de Resultados'!G21
A9: (-) ΔKTNO | B9: ='7. Indicadores Financieros'!B13 | C9: ='7. Indicadores Financieros'!C13 | D9: ='7. Indicadores Financieros'!D13 | E9: ='7. Indicadores Financieros'!E13 | F9: ='7. Indicadores Financieros'!F13 | G9: ='7. Indicadores Financieros'!G13
A10: (Flujo de Caja Operacional) | B10: =B7+B8-B9 | C10: =C7+C8-C9 | D10: =D7+D8-D9 | E10: =E7+E8-E9 | F10: =F7+F8-F9 | G10: =G7+G8-G9
A12: B. FLUJO DE CAJA DE INVERSIÓN (FCI)
A13: CAPEX (Inversión en PPE) | B13: N/A | C13: =('1. Balance General'!C7-'1. Balance General'!B7)+'2. Estado de Resultados'!C17 | D13: =('1. Balance General'!D7-'1. Balance General'!C7)+'2. Estado de Resultados'!D17 | E13: =('1. Balance General'!E7-'1. Balance General'!D7)+'2. Estado de Resultados'!E17 | F13: =('1. Balance General'!F7-'1. Balance General'!E7)+'2. Estado de Resultados'!F17 | G13: =('1. Balance General'!G7-'1. Balance General'!F7)+'2. Estado de Resultados'!G17
A14: (Flujo de Caja de Inversión) | B14: N/A | C14: =-C13 | D14: =-D13 | E14: =-E13 | F14: =-F13 | G14: =-G13
A16: C. FCFF - | B16: N/A | C16: =C10+C14 | D16: =D10+D14 | E16: =E10+E14 | F16: =F10+F14 | G16: =G10+G14
A18: D. FLUJO DE CAJA DE LA DEUDA (FCD)
A19: Variación Deuda Financiera | B19: N/A | C19: =(('1. Balance General'!C39+'1. Balance General'!C49)-('1. Balance General'!B39+'1. Balance General'!B49)) | D19: =(('1. Balance General'!D39+'1. Balance General'!D49)-('1. Balance General'!C39+'1. Balance General'!C49)) | E19: =(('1. Balance General'!E39+'1. Balance General'!E49)-('1. Balance General'!D39+'1. Balance General'!D49)) | F19: =(('1. Balance General'!F39+'1. Balance General'!F49)-('1. Balance General'!E39+'1. Balance General'!E49)) | G19: =(('1. Balance General'!G39+'1. Balance General'!G49)-('1. Balance General'!F39+'1. Balance General'!F49))
A20: (-) Intereses × (1-T) | B20: ='2. Estado de Resultados'!B13*0.65 | C20: ='2. Estado de Resultados'!C13*0.65 | D20: ='2. Estado de Resultados'!D13*0.65 | E20: ='2. Estado de Resultados'!E13*0.65 | F20: ='2. Estado de Resultados'!F13*0.65 | G20: ='2. Estado de Resultados'!G13*0.65
A21: =FCD (Flujo de Caja de la Deuda) | B21: N/A | C21: =C19+C20 | D21: =D19+D20 | E21: =E19+E20 | F21: =F19+F20 | G21: =G19+G20
A23: E. FCFE | B23: N/A | C23: =C16+C21 | D23: =D16+D21 | E23: =E16+E21 | F23: =F16+F21 | G23: =G16+G21
A26: CELSIA | B26: 0.55465 | C26: 0.55744382 | D26: 0.56436155 | E26: 0.57115808 | F26: 0.5744383 | G26: 0.58767
A27: Rm | B27: -0.0831 | C27: -0.08511 | D27: -0.09707 | E27: -0.08814 | F27: 0.0388 | G27: 0.0388
A28: Rf | B28: 0.15 | C28: 0.15132 | D28: 0.2813 | E28: 0.11863 | F28: 0.1454 | G28: 0.152

Sheet 9. Costo de Capital WACC
A1: ISAGEN S.A. E.S.P.
A2: COSTO DE CAPITAL Y WACC
A3: Weighted Average Cost of Capital
A5: PARÁMETRO | B5: 2020 | C5: 2021 | D5: 2022 | E5: 2023 | F5: 2024 | G5: 2025 (Sep)
A6: A. PARÁMETROS DE MERCADO
A7: Rf - Tasa Libre de Riesgo (TES 10 años) | B7: ='8. Flujos de Caja'!B28 | C7: ='8. Flujos de Caja'!C28 | D7: ='8. Flujos de Caja'!D28 | E7: ='8. Flujos de Caja'!E28 | F7: ='8. Flujos de Caja'!F28 | G7: ='8. Flujos de Caja'!G28
A8: Rm - Retorno del Mercado (COLCAP) | B8: ='8. Flujos de Caja'!B27 | C8: ='8. Flujos de Caja'!C27 | D8: ='8. Flujos de Caja'!D27 | E8: ='8. Flujos de Caja'!E27 | F8: ='8. Flujos de Caja'!F27 | G8: ='8. Flujos de Caja'!G27
A9: Prima de Riesgo de Mercado (Rm - Rf) | B9: =B8-B7 | C9: =C8-C7 | D9: =D8-D7 | E9: =E8-E7 | F9: =F8-F7 | G9: =G8-G7
A10: Riesgo País Colombia | B10: 0.025 | C10: 0.025 | D10: 0.025 | E10: 0.025 | F10: 0.025 | G10: 0.025
A11: Beta del Sector (Comparable: CELSIA) | B11: ='8. Flujos de Caja'!B26 | C11: ='8. Flujos de Caja'!C26 | D11: ='8. Flujos de Caja'!D26 | E11: ='8. Flujos de Caja'!E26 | F11: ='8. Flujos de Caja'!F26 | G11: ='8. Flujos de Caja'!G26
A13: B. ESTRUCTURA DE CAPITAL
A14: D - Deuda Financiera Total | B14: ='1. Balance General'!B39+'1. Balance General'!B49 | C14: ='1. Balance General'!C39+'1. Balance General'!C49 | D14: ='1. Balance General'!D39+'1. Balance General'!D49 | E14: ='1. Balance General'!E39+'1. Balance General'!E49 | F14: ='1. Balance General'!F39+'1. Balance General'!F49 | G14: ='1. Balance General'!G39+'1. Balance General'!G49
A15: E - Patrimonio Total | B15: ='1. Balance General'!B36 | C15: ='1. Balance General'!C36 | D15: ='1. Balance General'!D36 | E15: ='1. Balance General'!E36 | F15: ='1. Balance General'!F36 | G15: ='1. Balance General'!G36
A16: D + E (Valor Total) | B16: =B14+B15 | C16: =C14+C15 | D16: =D14+D15 | E16: =E14+E15 | F16: =F14+F15 | G16: =G14+G15
A17: D/E - Ratio Deuda/Patrimonio | B17: =B14/B15 | C17: =C14/C15 | D17: =D14/D15 | E17: =E14/E15 | F17: =F14/F15 | G17: =G14/G15
A18: % Deuda = D/(D+E) | B18: =B14/B16 | C18: =C14/C16 | D18: =D14/D16 | E18: =E14/E16 | F18: =F14/F16 | G18: =G14/G16
A19: % Patrimonio = E/(D+E) | B19: =B15/B16 | C19: =C15/C16 | D19: =D15/D16 | E19: =E15/E16 | F19: =F15/F16 | G19: =G15/G16
A21: C. COSTO DE LA DEUDA (Kd)
A22: Gastos Financieros | B22: ='2. Estado de Resultados'!B13 | C22: ='2. Estado de Resultados'!C13 | D22: ='2. Estado de Resultados'!D13 | E22: ='2. Estado de Resultados'!E13 | F22: ='2. Estado de Resultados'!F13 | G22: ='2. Estado de Resultados'!G13
A23: Kd - Costo de la Deuda (antes de impuestos) | B23: =ABS(B22/B14) | C23: =ABS(C22/C14) | D23: =ABS(D22/D14) | E23: =ABS(E22/E14) | F23: =ABS(F22/F14) | G23: =ABS(G22/G14)
A24: T - Tasa de Impuestos (efectiva) | B24: =ABS(('2. Estado de Resultados'!B20+'2. Estado de Resultados'!B21)/'2. Estado de Resultados'!B15) | C24: =ABS(('2. Estado de Resultados'!C20+'2. Estado de Resultados'!C21)/'2. Estado de Resultados'!C15) | D24: =ABS(('2. Estado de Resultados'!D20+'2. Estado de Resultados'!D21)/'2. Estado de Resultados'!D15) | E24: =ABS(('2. Estado de Resultados'!E20+'2. Estado de Resultados'!E21)/'2. Estado de Resultados'!E15) | F24: =ABS(('2. Estado de Resultados'!F20+'2. Estado de Resultados'!F21)/'2. Estado de Resultados'!F15) | G24: =ABS(('2. Estado de Resultados'!G20+'2. Estado de Resultados'!G21)/'2. Estado de Resultados'!G15)
A25: Kd (neto) = Kd × (1-T) | B25: =B23*(1-B24) | C25: =C23*(1-C24) | D25: =D23*(1-D24) | E25: =E23*(1-E24) | F25: =F23*(1-F24) | G25: =G23*(1-G24)
A27: D. BETA Y COSTO DEL PATRIMONIO (Ke)
A28: Bu - Beta Desapalancado | B28: =B11/(1+(1-B24)*B17) | C28: =C11/(1+(1-C24)*C17) | D28: =D11/(1+(1-D24)*D17) | E28: =E11/(1+(1-E24)*E17) | F28: =F11/(1+(1-F24)*F17) | G28: =G11/(1+(1-G24)*G17)
A29: BL - Beta Apalancado (ISAGEN) | B29: =B28*(1+(1-B24)*B17) | C29: =C28*(1+(1-C24)*C17) | D29: =D28*(1+(1-D24)*D17) | E29: =E28*(1+(1-E24)*E17) | F29: =F28*(1+(1-F24)*F17) | G29: =G28*(1+(1-G24)*G17)
A30: Ke - Costo del Patrimonio (CAPM) | B30: =B7+B29*B9+B10 | C30: =C7+C29*C9+C10 | D30: =D7+D29*D9+D10 | E30: =E7+E29*E9+E10 | F30: =F7+F29*F9+F10 | G30: =G7+G29*G9+G10
A32: E. WACC - COSTO PROMEDIO PONDERADO DE CAPITAL
A33: WACC | B33: =B30*B19+B25*B18 | C33: =C30*C19+C25*C18 | D33: =D30*D19+D25*D18 | E33: =E30*E19+E25*E18 | F33: =F30*F19+F25*F18 | G33: =G30*G19+G25*G18

Sheet 10. Valoración DCF
A1: ISAGEN S.A. E.S.P.
A2: VALORACIÓN POR FLUJOS DE CAJA DESCONTADOS (DCF)
A3: Proyecciones 2026-2035 y Valor Terminal
A5: CONCEPTO | B5: 2023 | C5: 2024 | D5: 2025 | E5: 2026 | F5: 2027 | G5: 2028 | H5: 2029 | I5: 2030 | J5: 2031 | K5: 2032 | L5: 2033 | M5: 2034 | N5: 2035
A6: A. SUPUESTOS DE PROYECCIÓN
A7: Tasa de Crecimiento FCFF (g) | B7: N/A | C7: N/A | D7: N/A | E7: 0.04 | F7: 0.04 | G7: 0.04 | H7: 0.04 | I7: 0.04 | J7: 0.04 | K7: 0.04 | L7: 0.04 | M7: 0.04 | N7: 0.04
A8: Tasa de Crecimiento Perpetuo (g terminal) | B8: 0.035 | C8: 0.035 | D8: 0.035 | E8: 0.035 | F8: 0.035 | G8: 0.035 | H8: 0.035 | I8: 0.035 | J8: 0.035 | K8: 0.035 | L8: 0.035 | M8: 0.035 | N8: 0.035
A10: B. FCFF
A11: FCFF | B11: ='8. Flujos de Caja'!E16 | C11: ='8. Flujos de Caja'!F16 | D11: ='8. Flujos de Caja'!G16 | E11: =AVERAGE(B11:D11) | F11: =E11*(1+F7) | G11: =F11*(1+G7) | H11: =G11*(1+H7) | I11: =H11*(1+I7) | J11: =I11*(1+J7) | K11: =J11*(1+K7) | L11: =K11*(1+L7) | M11: =L11*(1+M7) | N11: =M11*(1+N7)
A13: C. TASA DE DESCUENTO (WACC)
A14: WACC | B14: ='9. Costo de Capital WACC'!E33 | C14: ='9. Costo de Capital WACC'!F33 | D14: ='9. Costo de Capital WACC'!G33 | E14: ='14. WACC Proyectado'!C15 | F14: ='14. WACC Proyectado'!D15 | G14: ='14. WACC Proyectado'!E15 | H14: ='14. WACC Proyectado'!F15 | I14: ='14. WACC Proyectado'!G15 | J14: ='14. WACC Proyectado'!H15 | K14: ='14. WACC Proyectado'!I15 | L14: ='14. WACC Proyectado'!J15 | ... N14: ='14. WACC Proyectado'!L15
A15: Período (años desde 2025) | B15: -2 | C15: -1 | D15: 0 | E15: 1 | F15: 2 | G15: 3 | H15: 4 | I15: 5 | J15: 6 | K15: 7 | L15: 8 | M15: 9 | N15: 10
A16: Factor de Descuento = 1/(1+WACC)^n | B16: =1/((1+B14)^B15) | C16: =1/((1+C14)^C15) | D16: =1/((1+D14)^D15) | E16: ='14. WACC Proyectado'!C10 | F16: ='14. WACC Proyectado'!D10 | G16: ='14. WACC Proyectado'!E10 | H16: ='14. WACC Proyectado'!F10 | I16: ='14. WACC Proyectado'!G10 | J16: ='14. WACC Proyectado'!H10 | K16: ='14. WACC Proyectado'!I10 | L16: ='14. WACC Proyectado'!J10 | ... N16: ='14. WACC Proyectado'!L10
A17: FCFF Descontado (VP) | B17: =B11*B16 | C17: =C11*C16 | D17: =D11*D16 | E17: =E11*E16 | F17: =F11*F16 | G17: =G11*G16 | H17: =H11*H16 | I17: =I11*I16 | ... N17: =N11*N16
A19: D. VALOR TERMINAL (2035)
A20: FCFF 2036 = FCFF2035 × (1+g) | N20: =(N17*(1+N8))/(N14-N8)
A21: Valor Operación | B21: =(C21+B17)/(1+B14) | C21: =(D21+C17)/(1+C14) | D21: =(E21+D17)/(1+D14) | E21: =(F21+E17)/(1+E14) | F21: =(G21+F17)/(1+F14) | G21: =(H21+G17)/(1+G14) | H21: =(I21+H17)/(1+H14) | I21: =(J21+I17)/(1+I14) | ... M21: =(N21+M17)/(1+M14) | N21: =(N20+N17)/(1+N14)
A22: (+) Otros activos | N22: =N21*N16
A23: (-) Otros pasivos
A24: E. VALORACIÓN DE LA EMPRESA
A25: Valor Presente FCFF Proyectados | N25: =SUM(E17:N17)
A26: (+) Valor Terminal Descontado | N26: =N22
A27: =VALOR de OPERACIÓN (Enterprise Value) | N27: =N25+N22
A29: (-) Deuda Financiera Neta | N29: ='1. Balance General'!F38+'1. Balance General'!F49-'1. Balance General'!F24
A30: (+) Activos No Operacionales | N30: 0
A31: =VALOR PATRIMONIAL (Equity Value) | N31: =N27-N29+N30

Sheet 11. Análisis Sensibilidad
A1: ISAGEN S.A. E.S.P.
A2: ANÁLISIS DE SENSIBILIDAD DEL VALOR PATRIMONIAL
A3: Variaciones en WACC y Tasa de Crecimiento Perpetuo (g)
A5: VALORES BASE DEL MODELO
A6: WACC Base (2024) | B6: ='9. Costo de Capital WACC'!F39
A7: Tasa Crecimiento Perpetuo Base (g) | B7: ='10. Valoración DCF'!N9
A8: Valor Patrimonial Base | B8: ='10. Valoración DCF'!N32
A11: TABLA DE SENSIBILIDAD: VALOR PATRIMONIAL
A12: Variación en WACC y Tasa de Crecimiento Perpetuo (g)
A13: WACC \ g | B13: g-2.0% | C13: g-1.0% | D13: g-0.5% | E13: BASE | F13: g+0.5% | G13: g+1.0% | H13: g+2.0%
A14: WACC-2.0% | B14: =$B$8*(1+-0.02*10)*(1--0.02*20) | C14: =$B$8*(1+-0.01*10)*(1--0.02*20) | D14: =$B$8*(1+-0.005*10)*(1--0.02*20) | E14: =$B$8*(1+0*10)*(1--0.02*20) | F14: =$B$8*(1+0.005*10)*(1--0.02*20) | G14: =$B$8*(1+0.01*10)*(1--0.02*20) | H14: =$B$8*(1+0.02*10)*(1--0.02*20)
A15: WACC-1.0% | B15: =$B$8*(1+-0.02*10)*(1--0.01*20) | C15: =$B$8*(1+-0.01*10)*(1--0.01*20) | D15: =$B$8*(1+-0.005*10)*(1--0.01*20) | E15: =$B$8*(1+0*10)*(1--0.01*20) | F15: =$B$8*(1+0.005*10)*(1--0.01*20) | G15: =$B$8*(1+0.01*10)*(1--0.01*20) | H15: =$B$8*(1+0.02*10)*(1--0.01*20)
A16: BASE | B16: =$B$8*(1+-0.02*10)*(1-0*20) | C16: =$B$8*(1+-0.01*10)*(1-0*20) | D16: =$B$8*(1+-0.005*10)*(1-0*20) | E16: =$B$8*(1+0*10)*(1-0*20) | F16: =$B$8*(1+0.005*10)*(1-0*20) | G16: =$B$8*(1+0.01*10)*(1-0*20) | H16: =$B$8*(1+0.02*10)*(1-0*20)
A17: WACC+1.0% | B17: =$B$8*(1+-0.02*10)*(1-0.01*20) | C17: =$B$8*(1+-0.01*10)*(1-0.01*20) | D17: =$B$8*(1+-0.005*10)*(1-0.01*20) | E17: =$B$8*(1+0*10)*(1-0.01*20) | F17: =$B$8*(1+0.005*10)*(1-0.01*20) | G17: =$B$8*(1+0.01*10)*(1-0.01*20) | H17: =$B$8*(1+0.02*10)*(1-0.01*20)
A18: WACC+2.0% | B18: =$B$8*(1+-0.02*10)*(1-0.02*20) | C18: =$B$8*(1+-0.01*10)*(1-0.02*20) | D18: =$B$8*(1+-0.005*10)*(1-0.02*20) | E18: =$B$8*(1+0*10)*(1-0.02*20) | F18: =$B$8*(1+0.005*10)*(1-0.02*20) | G18: =$B$8*(1+0.01*10)*(1-0.02*20) | H18: =$B$8*(1+0.02*10)*(1-0.02*20)
A21: INTERPRETACIÓN DEL ANÁLISIS DE SENSIBILIDAD
A22: NOTAS IMPORTANTES: 1. La tabla muestra cómo varía el Valor Patrimonial de ISAGEN según cambios en: - WACC (Costo Promedio Ponderado de Capital) - g (Tasa de Crecimiento Perpetuo) 2. SENSIBILIDAD AL WACC: - Un aumento en el WACC reduce el valor de la empresa (mayor costo de capital = menor valor) - Una disminución en el WACC aumenta el valor de la empresa 3. SENSIBILIDAD A LA TASA DE CRECIMIENTO (g): - Un aumento en g aumenta el valor terminal y por ende el valor de la empresa - Una disminución en g reduce el valor terminal 4. LIMITACIONES: - Esta tabla proporciona una aproximación de la sensibilidad - Para un análisis exacto, cada celda requeriría recalcular todo el modelo DCF - Se recomienda validar los rangos razonables de WACC y g según el sector energético 5. RANGO RAZONABLE PARA ISAGEN (Sector Energía): - WACC: 7% - 12% (típico para empresas de servicios públicos en Colombia) - g: 2.5% - 4.5% (considerando inflación y crecimiento económico de Colombia)

Sheet 14. WACC Proyectado
A1: WACC PROYECTADO (2026-2035)
A3: CONCEPTO | B3: 2025 | C3: 2026 | D3: 2027 | E3: 2028 | F3: 2029 | G3: 2030 | H3: 2031 | I3: 2032 | J3: 2033 | K3: 2034 | L3: 2035
A5: Deuda (D) | B5: ='13. BSC Proyectado'!B38+'13. BSC Proyectado'!B48 | C5: ='13. BSC Proyectado'!C38+'13. BSC Proyectado'!C48 | D5: ='13. BSC Proyectado'!D38+'13. BSC Proyectado'!D48 | E5: ='13. BSC Proyectado'!E38+'13. BSC Proyectado'!E48 | F5: ='13. BSC Proyectado'!F38+'13. BSC Proyectado'!F48 | G5: ='13. BSC Proyectado'!G38+'13. BSC Proyectado'!G48 | H5: ='13. BSC Proyectado'!H38+'13. BSC Proyectado'!H48 | I5: ='13. BSC Proyectado'!I38+'13. BSC Proyectado'!I48 | ... L5: ='13. BSC Proyectado'!L38+'13. BSC Proyectado'!L48
A6: Patrimonio (E) | B6: ='13. BSC Proyectado'!B35 | C6: ='13. BSC Proyectado'!C35 | D6: ='13. BSC Proyectado'!D35 | E6: ='13. BSC Proyectado'!E35 | F6: ='13. BSC Proyectado'!F35 | G6: ='13. BSC Proyectado'!G35 | H6: ='13. BSC Proyectado'!H35 | I6: ='13. BSC Proyectado'!I35 | ... L6: ='13. BSC Proyectado'!L35
A10: WACC | B10: =B6/(B5+B6)*='9. Costo de Capital WACC'!F37 + B5/(B5+B6)*='9. Costo de Capital WACC'!F33 | C10: =C6/(C5+C6)*='9. Costo de Capital WACC'!F37 + C5/(C5+C6)*='9. Costo de Capital WACC'!F33 | D10: =D6/(D5+D6)*='9. Costo de Capital WACC'!F37 + D5/(D5+D6)*='9. Costo de Capital WACC'!F33 | E10: =E6/(E5+E6)*='9. Costo de Capital WACC'!F37 + E5/(E5+E6)*='9. Costo de Capital WACC'!F33 | F10: =F6/(F5+F6)*='9. Costo de Capital WACC'!F37 + F5/(F5+F6)*='9. Costo de Capital WACC'!F33 | G10: =G6/(G5+G6)*='9. Costo de Capital WACC'!F37 + G5/(G5+G6)*='9. Costo de Capital WACC'!F33 | H10: =H6/(H5+H6)*='9. Costo de Capital WACC'!F37 + H5/(H5+H6)*='9. Costo de Capital WACC'!F33 | I10: =I6/(I5+I6)*='9. Costo de Capital WACC'!F37 + I5/(I5+I6)*='9. Costo de Capital WACC'!F33 | J10: =J6/(J5+J6)*='9. Costo de Capital WACC'!F37 + J5/(J5+J6)*='9. Costo de Capital WACC'!F33 | K10: =K6/(K5+K6)*='9. Costo de Capital WACC'!F37 + K5/(K5+K6)*='9. Costo de Capital WACC'!F33 | L10: =L6/(L5+L6)*='9. Costo de Capital WACC'!F37 + L5/(L5+L6)*='9. Costo de Capital WACC'!F33

Sheet 12. ER Proyectado
A1: ESTADO DE RESULTADOS PROYECTADO (2026-2035)
A3: CONCEPTO | B3: 2025 | C3: 2026 | D3: 2027 | E3: 2028 | F3: 2029 | G3: 2030 | H3: 2031 | I3: 2032 | J3: 2033 | K3: 2034 | L3: 2035
A4: Ingresos de contratos con clientes | B4: ='2. Estado de Resultados'!G6/9*12 | C4: =B4*(1+0.04) | D4: =C4*(1+0.04) | E4: =D4*(1+0.04) | F4: =E4*(1+0.04) | G4: =F4*(1+0.04) | H4: =G4*(1+0.04) | I4: =H4*(1+0.04) | J4: =I4*(1+0.04) | ... L4: =K4*(1+0.04)
A5: Costo de ventas | B5: ='2. Estado de Resultados'!G7/9*12 | C5: =C4*(B5/B4) | D5: =D4*(C5/C4) | E5: =E4*(D5/D4) | F5: =F4*(E5/E4) | G5: =G4*(F5/F4) | H5: =H4*(G5/G4) | I5: =I4*(H5/H4) | J5: =J4*(I5/I4) | ... L5: =L4*(K5/K4)
A6: Utilidad Bruta | B6: ='2. Estado de Resultados'!G8/9*12 | C6: =C4+C5 | D6: =D4+D5 | E6: =E4+E5 | F6: =F4+F5 | G6: =G4+G5 | H6: =H4+H5 | I6: =I4+I5 | J6: =J4+J5 | ... L6: =L4+L5
A7: Otros ingresos | B7: ='2. Estado de Resultados'!G9/9*12
A8: Gastos de administración | B8: ='2. Estado de Resultados'!G10/9*12 | C8: =C4*(B8/B4) | D8: =D4*(C8/C4) | E8: =E4*(D8/D4) | F8: =F4*(E8/E4) | G8: =G4*(F8/F4) | H8: =H4*(G8/G4) | I8: =I4*(H8/H4) | J8: =J4*(I8/I4) | ... L8: =L4*(K8/K4)
A9: Otros gastos | B9: ='2. Estado de Resultados'!G11/9*12 | C9: =C4*(B9/B4) | D9: =D4*(C9/C4) | E9: =E4*(D9/D4) | F9: =F4*(E9/E4) | G9: =G4*(F9/F4) | H9: =H4*(G9/G4) | I9: =I4*(H9/H4) | J9: =J4*(I9/I4) | ... L9: =L4*(K9/K4)
A10: Ingresos financieros | B10: ='2. Estado de Resultados'!G12/9*12
A11: Gastos financieros | B11: ='2. Estado de Resultados'!G13/9*12 | C11: =-('13. BSC Proyectado'!B38 + '13. BSC Proyectado'!B48)*0.14 | D11: =-('13. BSC Proyectado'!C38 + '13. BSC Proyectado'!C48)*0.14 | E11: =-('13. BSC Proyectado'!D38 + '13. BSC Proyectado'!D48)*0.14 | F11: =-('13. BSC Proyectado'!E38 + '13. BSC Proyectado'!E48)*0.14 | G11: =-('13. BSC Proyectado'!F38 + '13. BSC Proyectado'!F48)*0.14 | H11: =-('13. BSC Proyectado'!G38 + '13. BSC Proyectado'!G48)*0.14 | I11: =-('13. BSC Proyectado'!H38 + '13. BSC Proyectado'!H48)*0.14 | J11: =-('13. BSC Proyectado'!I38 + '13. BSC Proyectado'!I48)*0.14 | ... L11: =-('13. BSC Proyectado'!K38 + '13. BSC Proyectado'!K48)*0.14
A12: Diferencia en cambio, neta | B12: ='2. Estado de Resultados'!G14/9*12
A13: Utilidad Antes de Impuestos | B13: ='2. Estado de Resultados'!G15/9*12 | C13: =SUM(C6:C12) | D13: =SUM(D6:D12) | E13: =SUM(E6:E12) | F13: =SUM(F6:F12) | G13: =SUM(G6:G12) | H13: =SUM(H6:H12) | I13: =SUM(I6:I12) | J13: =SUM(J6:J12) | ... L13: =SUM(L6:L12)
A14: EBIT | B14: ='2. Estado de Resultados'!G16/9*12 | C14: =C6+C7+C8+C9 | D14: =D6+D7+D8+D9 | E14: =E6+E7+E8+E9 | F14: =F6+F7+F8+F9 | G14: =G6+G7+G8+G9 | H14: =H6+H7+H8+H9 | I14: =I6+I7+I8+I9 | J14: =J6+J7+J8+J9 | ... L14: =L6+L7+L8+L9
A15: Depreciación | B15: ='2. Estado de Resultados'!G17/9*12
A16: Amortización | B16: ='2. Estado de Resultados'!G18/9*12
A17: EBITDA | B17: ='2. Estado de Resultados'!G19/9*12
A18: Impuesto de renta - Corriente | B18: ='2. Estado de Resultados'!G20/9*12 | C18: =-C13*0.35 | D18: =-D13*0.35 | E18: =-E13*0.35 | F18: =-F13*0.35 | G18: =-G13*0.35 | H18: =-H13*0.35 | I18: =-I13*0.35 | J18: =-J13*0.35 | ... L18: =-L13*0.35
A19: Impuesto de renta - Diferido | B19: ='2. Estado de Resultados'!G21/9*12
A20: Utilidad Neta del Periodo | B20: ='2. Estado de Resultados'!G22/9*12 | C20: =C13+SUM(C18:C19) | D20: =D13+SUM(D18:D19) | E20: =E13+SUM(E18:E19) | F20: =F13+SUM(F18:F19) | G20: =G13+SUM(G18:G19) | H20: =H13+SUM(H18:H19) | I20: =I13+SUM(I18:I19) | J20: =J13+SUM(J18:J19) | ... L20: =L13+SUM(L18:L19)
B21: ='2. Estado de Resultados'!G23/9*12
B22: ='2. Estado de Resultados'!G24/9*12
A23: OTRO RESULTADO INTEGRAL (ORI) | B23: ='2. Estado de Resultados'!G25/9*12
A24: Ganancias actuariales (Beneficios definidos) | B24: ='2. Estado de Resultados'!G26/9*12
A25: Coberturas flujo de efectivo | B25: ='2. Estado de Resultados'!G27/9*12
A26: Total Otro Resultado Integral, neto | B26: ='2. Estado de Resultados'!G28/9*12
A27: RESULTADO INTEGRAL TOTAL | B27: ='2. Estado de Resultados'!G29/9*12
B28: ='2. Estado de Resultados'!G30/9*12
A29: Utilidad básica y diluida por acción ($) | B29: ='2. Estado de Resultados'!G31/9*12

Sheet 13. BSC Proyectado
A1: CONTROL (Activo - Pasivo - Patrimonio) | C1: =C26-C59 | D1: =D26-D59 | E1: =E26-E59 | F1: =F26-F59 | G1: =G26-G59 | H1: =H26-H59 | I1: =I26-I59 | J1: =J26-J59 | ... L1: =L26-L59
A2: BALANCE GENERAL PROYECTADO (2026-2035)
A4: CONCEPTO | B4: 2025 | C4: 2026 | D4: 2027 | E4: 2028 | F4: 2029 | G4: 2030 | H4: 2031 | I4: 2032 | J4: 2033 | K4: 2034 | L4: 2035
A5: ACTIVOS NO CORRIENTES | B5: ='1. Balance General'!G6 | C5: =B5 | D5: =C5 | E5: =D5 | F5: =E5 | G5: =F5 | H5: =G5 | I5: =H5 | J5: =I5 | ... L5: =K5
A6: Propiedades, planta y equipo, neto | B6: ='1. Balance General'!G7 | C6: =B6 + '12. ER Proyectado'!C4*0.05 - B6*0.05 | D6: =C6 + '12. ER Proyectado'!D4*0.05 - C6*0.05 | E6: =D6 + '12. ER Proyectado'!E4*0.05 - D6*0.05 | F6: =E6 + '12. ER Proyectado'!F4*0.05 - E6*0.05 | G6: =F6 + '12. ER Proyectado'!G4*0.05 - F6*0.05 | H6: =G6 + '12. ER Proyectado'!H4*0.05 - G6*0.05 | I6: =H6 + '12. ER Proyectado'!I4*0.05 - H6*0.05 | J6: =I6 + '12. ER Proyectado'!J4*0.05 - I6*0.05 | ... L6: =K6 + '12. ER Proyectado'!L4*0.05 - K6*0.05
A7: Activos intangibles, neto | B7: ='1. Balance General'!G8 | C7: =B7 | D7: =C7 | E7: =D7 | F7: =E7 | G7: =F7 | H7: =G7 | I7: =H7 | J7: =I7 | ... L7: =K7
A8: Cuentas por cobrar, neto | B8: ='1. Balance General'!G9 | C8: =B8 | D8: =C8 | E8: =D8 | F8: =E8 | G8: =F8 | H8: =G8 | I8: =H8 | J8: =I8 | ... L8: =K8
A9: Instrumentos financieros | B9: ='1. Balance General'!G10 | C9: =B9 | D9: =C9 | E9: =D9 | F9: =E9 | G9: =F9 | H9: =G9 | I9: =H9 | J9: =I9 | ... L9: =K9
A10: Operaciones con derivados | B10: ='1. Balance General'!G11 | C10: =B10 | D10: =C10 | E10: =D10 | F10: =E10 | G10: =F10 | H10: =G10 | I10: =H10 | J10: =I10 | ... L10: =K10
A11: Efectivo restringido | B11: ='1. Balance General'!G12 | C11: =B11 | D11: =C11 | E11: =D11 | F11: =E11 | G11: =F11 | H11: =G11 | I11: =H11 | J11: =I11 | ... L11: =K11
A12: Otros activos | B12: ='1. Balance General'!G13 | C12: =B12 | D12: =C12 | E12: =D12 | F12: =E12 | G12: =F12 | H12: =G12 | I12: =H12 | J12: =I12 | ... L12: =K12
A13: Total Activos No Corrientes | B13: ='1. Balance General'!G14 | C13: =SUM(C5:C12) | D13: =SUM(D5:D12) | E13: =SUM(E5:E12) | F13: =SUM(F5:F12) | G13: =SUM(G5:G12) | H13: =SUM(H5:H12) | I13: =SUM(I5:I12) | J13: =SUM(J5:J12) | ... L13: =SUM(L5:L12)
B14: ='1. Balance General'!G15 | C14: =B14 | D14: =C14 | E14: =D14 | F14: =E14 | G14: =F14 | H14: =G14 | I14: =H14 | J14: =I14 | ... L14: =K14
A15: ACTIVOS CORRIENTES | B15: ='1. Balance General'!G16 | C15: =B15 | D15: =C15 | E15: =D15 | F15: =E15 | G15: =F15 | H15: =G15 | I15: =H15 | J15: =I15 | ... L15: =K15
A16: Inventarios | B16: ='1. Balance General'!G17 | C16: =-'12. ER Proyectado'!C5/360 * 40 | D16: =-'12. ER Proyectado'!D5/360 * 40 | E16: =-'12. ER Proyectado'!E5/360 * 40 | F16: =-'12. ER Proyectado'!F5/360 * 40 | G16: =-'12. ER Proyectado'!G5/360 * 40 | H16: =-'12. ER Proyectado'!H5/360 * 40 | I16: =-'12. ER Proyectado'!I5/360 * 40 | J16: =-'12. ER Proyectado'!J5/360 * 40 | ... L16: =-'12. ER Proyectado'!L5/360 * 40
A17: Cuentas por cobrar, neto | B17: ='1. Balance General'!G18 | C17: ='12. ER Proyectado'!C4/360 * 60 | D17: ='12. ER Proyectado'!D4/360 * 60 | E17: ='12. ER Proyectado'!E4/360 * 60 | F17: ='12. ER Proyectado'!F4/360 * 60 | G17: ='12. ER Proyectado'!G4/360 * 60 | H17: ='12. ER Proyectado'!H4/360 * 60 | I17: ='12. ER Proyectado'!I4/360 * 60 | J17: ='12. ER Proyectado'!J4/360 * 60 | ... L17: ='12. ER Proyectado'!L4/360 * 60
A18: Instrumentos financieros | B18: ='1. Balance General'!G19 | C18: =B18 | D18: =C18 | E18: =D18 | F18: =E18 | G18: =F18 | H18: =G18 | I18: =H18 | J18: =I18 | ... L18: =K18
A19: Activos por impuestos | B19: ='1. Balance General'!G20 | C19: =B19 | D19: =C19 | E19: =D19 | F19: =E19 | G19: =F19 | H19: =G19 | I19: =H19 | J19: =I19 | ... L19: =K19
A20: Otros activos | B20: ='1. Balance General'!G21 | C20: =B20 | D20: =C20 | E20: =D20 | F20: =E20 | G20: =F20 | H20: =G20 | I20: =H20 | J20: =I20 | ... L20: =K20
A21: Operaciones con derivados | B21: ='1. Balance General'!G22 | C21: =B21 | D21: =C21 | E21: =D21 | F21: =E21 | G21: =F21 | H21: =G21 | I21: =H21 | J21: =I21 | ... L21: =K21
A22: Efectivo restringido | B22: ='1. Balance General'!G23 | C22: =B22 | D22: =C22 | E22: =D22 | F22: =E22 | G22: =F22 | H22: =G22 | I22: =H22 | J22: =I22 | ... L22: =K22
A23: Efectivo y equivalentes de efectivo | B23: ='1. Balance General'!G24 | C23: =C59 - (SUM(C15:C22) + C13) | D23: =D59 - (SUM(D15:D22) + D13) | E23: =E59 - (SUM(E15:E22) + E13) | F23: =F59 - (SUM(F15:F22) + F13) | G23: =G59 - (SUM(G15:G22) + G13) | H23: =H59 - (SUM(H15:H22) + H13) | I23: =I59 - (SUM(I15:I22) + I13) | J23: =J59 - (SUM(J15:J22) + J13) | ... L23: =L59 - (SUM(L15:L22) + L13)
A24: Total Activos Corrientes | B24: ='1. Balance General'!G25 | C24: =SUM(C15:C23) | D24: =SUM(D15:D23) | E24: =SUM(E15:E23) | F24: =SUM(F15:F23) | G24: =SUM(G15:G23) | H24: =SUM(H15:H23) | I24: =SUM(I15:I23) | J24: =SUM(J15:J23) | ... L24: =SUM(L15:L23)
B25: ='1. Balance General'!G26 | C25: =B25 | D25: =C25 | E25: =D25 | F25: =E25 | G25: =F25 | H25: =G25 | I25: =H25 | J25: =I25 | ... L25: =K25
A26: TOTAL ACTIVOS | B26: ='1. Balance General'!G27 | C26: =C13+C24 | D26: =D13+D24 | E26: =E13+E24 | F26: =F13+F24 | G26: =G13+G24 | H26: =H13+H24 | I26: =I13+I24 | J26: =J13+J24 | ... L26: =L13+L24
B27: ='1. Balance General'!G28 | C27: =B27 | D27: =C27 | E27: =D27 | F27: =E27 | G27: =F27 | H27: =G27 | I27: =H27 | J27: =I27 | ... L27: =K27
A28: PATRIMONIO | B28: ='1. Balance General'!G29 | C28: =B28 | D28: =C28 | E28: =D28 | F28: =E28 | G28: =F28 | H28: =G28 | I28: =H28 | J28: =I28 | ... L28: =K28
A29: Capital | B29: ='1. Balance General'!G30 | C29: =B29 | D29: =C29 | E29: =D29 | F29: =E29 | G29: =F29 | H29: =G29 | I29: =H29 | J29: =I29 | ... L29: =K29
A30: Reservas | B30: ='1. Balance General'!G31 | C30: =B30 | D30: =C30 | E30: =D30 | F30: =E30 | G30: =F30 | H30: =G30 | I30: =H30 | J30: =I30 | ... L30: =K30
A31: Superávit de capital | B31: ='1. Balance General'!G32 | C31: =B31 | D31: =C31 | E31: =D31 | F31: =E31 | G31: =F31 | H31: =G31 | I31: =H31 | J31: =I31 | ... L31: =K31
A32: Ganancias retenidas | B32: ='1. Balance General'!G33 | C32: =B32 + '12. ER Proyectado'!C20 | D32: =C32 + '12. ER Proyectado'!D20 | E32: =D32 + '12. ER Proyectado'!E20 | F32: =E32 + '12. ER Proyectado'!F20 | G32: =F32 + '12. ER Proyectado'!G20 | H32: =G32 + '12. ER Proyectado'!H20 | I32: =H32 + '12. ER Proyectado'!I20 | J32: =I32 + '12. ER Proyectado'!J20 | ... L32: =K32 + '12. ER Proyectado'!L20
A33: Otro resultado integral | B33: ='1. Balance General'!G34 | C33: =B33 | D33: =C33 | E33: =D33 | F33: =E33 | G33: =F33 | H33: =G33 | I33: =H33 | J33: =I33 | ... L33: =K33
A34: Resultado integral total periodo (Utilidad Neta) | B34: ='1. Balance General'!G35 | C34: =B34 | D34: =C34 | E34: =D34 | F34: =E34 | G34: =F34 | H34: =G34 | I34: =H34 | J34: =I34 | ... L34: =K34
A35: Total Patrimonio de los Accionistas | B35: ='1. Balance General'!G36 | C35: =SUM(C29:C34) | D35: =SUM(D29:D34) | E35: =SUM(E29:E34) | F35: =SUM(F29:F34) | G35: =SUM(G29:G34) | H35: =SUM(H29:H34) | I35: =SUM(I29:I34) | J35: =SUM(J29:J34) | ... L35: =SUM(L29:L34)
B36: ='1. Balance General'!G37 | C36: =B36 | D36: =C36 | E36: =D36 | F36: =E36 | G36: =F36 | H36: =G36 | I36: =H36 | J36: =I36 | ... L36: =K36
A37: PASIVOS NO CORRIENTES | B37: ='1. Balance General'!G38 | C37: =B37 | D37: =C37 | E37: =D37 | F37: =E37 | G37: =F37 | H37: =G37 | I37: =H37 | J37: =I37 | ... L37: =K37
A38: Operaciones de financiamiento | B38: ='1. Balance General'!G39 | C38: =B38 | D38: =C38 | E38: =D38 | F38: =E38 | G38: =F38 | H38: =G38 | I38: =H38 | J38: =I38 | ... L38: =K38
A39: Obligaciones con vinculados | B39: ='1. Balance General'!G40 | C39: =B39 | D39: =C39 | E39: =D39 | F39: =E39 | G39: =F39 | H39: =G39 | I39: =H39 | J39: =I39 | ... L39: =K39
A40: Operaciones con derivados | B40: ='1. Balance General'!G41 | C40: =B40 | D40: =C40 | E40: =D40 | F40: =E40 | G40: =F40 | H40: =G40 | I40: =H40 | J40: =I40 | ... L40: =K40
A41: Impuestos, contribuciones y tasas | B41: ='1. Balance General'!G42 | C41: =B41 | D41: =C41 | E41: =D41 | F41: =E41 | G41: =F41 | H41: =G41 | I41: =H41 | J41: =I41 | ... L41: =K41
A42: Beneficios a empleados | B42: ='1. Balance General'!G43 | C42: =B42 | D42: =C42 | E42: =D42 | F42: =E42 | G42: =F42 | H42: =G42 | I42: =H42 | J42: =I42 | ... L42: =K42
A43: Provisiones | B43: ='1. Balance General'!G44 | C43: =B43 | D43: =C43 | E43: =D43 | F43: =E43 | G43: =F43 | H43: =G43 | I43: =H43 | J43: =I43 | ... L43: =K43
A44: Cuentas por pagar | B44: ='1. Balance General'!G45 | C44: =B44 | D44: =C44 | E44: =D44 | F44: =E44 | G44: =F44 | H44: =G44 | I44: =H44 | J44: =I44 | ... L44: =K44
A45: Total Pasivos No Corrientes | B45: ='1. Balance General'!G46 | C45: =SUM(C37:C44) | D45: =SUM(D37:D44) | E45: =SUM(E37:E44) | F45: =SUM(F37:F44) | G45: =SUM(G37:G44) | H45: =SUM(H37:H44) | I45: =SUM(I37:I44) | J45: =SUM(J37:J44) | ... L45: =SUM(L37:L44)
B46: ='1. Balance General'!G47 | C46: =B46 | D46: =C46 | E46: =D46 | F46: =E46 | G46: =F46 | H46: =G46 | I46: =H46 | J46: =I46 | ... L46: =K46
A47: PASIVOS CORRIENTES | B47: ='1. Balance General'!G48 | C47: =B47 | D47: =C47 | E47: =D47 | F47: =E47 | G47: =F47 | H47: =G47 | I47: =H47 | J47: =I47 | ... L47: =K47
A48: Operaciones de financiamiento | B48: ='1. Balance General'!G49 | C48: =B48 | D48: =C48 | E48: =D48 | F48: =E48 | G48: =F48 | H48: =G48 | I48: =H48 | J48: =I48 | ... L48: =K48
A49: Cuentas por pagar | B49: ='1. Balance General'!G50 | C49: =-'12. ER Proyectado'!C5/360 * 45 | D49: =-'12. ER Proyectado'!D5/360 * 45 | E49: =-'12. ER Proyectado'!E5/360 * 45 | F49: =-'12. ER Proyectado'!F5/360 * 45 | G49: =-'12. ER Proyectado'!G5/360 * 45 | H49: =-'12. ER Proyectado'!H5/360 * 45 | I49: =-'12. ER Proyectado'!I5/360 * 45 | J49: =-'12. ER Proyectado'!J5/360 * 45 | ... L49: =-'12. ER Proyectado'!L5/360 * 45
A50: Obligaciones con vinculados | B50: ='1. Balance General'!G51 | C50: =B50 | D50: =C50 | E50: =D50 | F50: =E50 | G50: =F50 | H50: =G50 | I50: =H50 | J50: =I50 | ... L50: =K50
A51: Operaciones con derivados | B51: ='1. Balance General'!G52 | C51: =B51 | D51: =C51 | E51: =D51 | F51: =E51 | G51: =F51 | H51: =G51 | I51: =H51 | J51: =I51 | ... L51: =K51
A52: Impuestos, contribuciones y tasas | B52: ='1. Balance General'!G53 | C52: =B52 | D52: =C52 | E52: =D52 | F52: =E52 | G52: =F52 | H52: =G52 | I52: =H52 | J52: =I52 | ... L52: =K52
A53: Beneficios a empleados | B53: ='1. Balance General'!G54 | C53: =B53 | D53: =C53 | E53: =D53 | F53: =E53 | G53: =F53 | H53: =G53 | I53: =H53 | J53: =I53 | ... L53: =K53
A54: Provisiones | B54: ='1. Balance General'!G55 | C54: =B54 | D54: =C54 | E54: =D54 | F54: =E54 | G54: =F54 | H54: =G54 | I54: =H54 | J54: =I54 | ... L54: =K54
A55: Otros pasivos | B55: ='1. Balance General'!G56 | C55: =B55 | D55: =C55 | E55: =D55 | F55: =E55 | G55: =F55 | H55: =G55 | I55: =H55 | J55: =I55 | ... L55: =K55
A56: Total Pasivos Corrientes | B56: ='1. Balance General'!G57 | C56: =SUM(C47:C55) | D56: =SUM(D47:D55) | E56: =SUM(E47:E55) | F56: =SUM(F47:F55) | G56: =SUM(G47:G55) | H56: =SUM(H47:H55) | I56: =SUM(I47:I55) | J56: =SUM(J47:J55) | ... L56: =SUM(L47:L55)
B57: ='1. Balance General'!G58 | C57: =B57 | D57: =C57 | E57: =D57 | F57: =E57 | G57: =F57 | H57: =G57 | I57: =H57 | J57: =I57 | ... L57: =K57
A58: TOTAL PASIVOS | B58: ='1. Balance General'!G59 | C58: =C45+C56 | D58: =D45+D56 | E58: =E45+E56 | F58: =F45+F56 | G58: =G45+G56 | H58: =H45+H56 | I58: =I45+I56 | J58: =J45+J56 | ... L58: =L45+L56
A59: TOTAL PATRIMONIO Y PASIVOS | B59: ='1. Balance General'!G60 | C59: =C58+C35 | D59: =D58+D35 | E59: =E58+E35 | F59: =F58+F35 | G59: =G58+G35 | H59: =H58+H35 | I59: =I58+I35 | J59: =J58+J35 | ... L59: =L58+L35
